{
"meta":{"test_sets":[],"test_metrics":[],"learn_metrics":[{"best_value":"Min","name":"RMSE"}],"launch_mode":"Train","parameters":"","iteration_count":1000,"learn_sets":["learn"],"name":"experiment"},
"iterations":[
{"learn":[14.59871775],"iteration":0,"passed_time":0.05725460457,"remaining_time":57.19734997},
{"learn":[14.22518863],"iteration":1,"passed_time":0.05769324203,"remaining_time":28.78892777},
{"learn":[13.8866124],"iteration":2,"passed_time":0.05822166518,"remaining_time":19.34900006},
{"learn":[13.52356875],"iteration":3,"passed_time":0.05861684721,"remaining_time":14.59559495},
{"learn":[13.18870211],"iteration":4,"passed_time":0.05896949039,"remaining_time":11.73492859},
{"learn":[12.9124226],"iteration":5,"passed_time":0.05938283787,"remaining_time":9.837756807},
{"learn":[12.60003351],"iteration":6,"passed_time":0.05980026841,"remaining_time":8.483095219},
{"learn":[12.32990573],"iteration":7,"passed_time":0.06002150368,"remaining_time":7.442666457},
{"learn":[12.0660619],"iteration":8,"passed_time":0.06037648005,"remaining_time":6.648121303},
{"learn":[11.77309809],"iteration":9,"passed_time":0.06076091278,"remaining_time":6.015330366},
{"learn":[11.49227636],"iteration":10,"passed_time":0.0611956755,"remaining_time":5.502047552},
{"learn":[11.26264833],"iteration":11,"passed_time":0.06155211011,"remaining_time":5.067790399},
{"learn":[11.04260393],"iteration":12,"passed_time":0.0619957889,"remaining_time":4.706911049},
{"learn":[10.79916926],"iteration":13,"passed_time":0.06239742882,"remaining_time":4.394561773},
{"learn":[10.5541002],"iteration":14,"passed_time":0.06276161291,"remaining_time":4.121345914},
{"learn":[10.31918115],"iteration":15,"passed_time":0.06304051101,"remaining_time":3.876991427},
{"learn":[10.10004441],"iteration":16,"passed_time":0.06339057103,"remaining_time":3.665466548},
{"learn":[9.894556723],"iteration":17,"passed_time":0.06375171365,"remaining_time":3.478010156},
{"learn":[9.690174082],"iteration":18,"passed_time":0.06404848556,"remaining_time":3.306924439},
{"learn":[9.506034866],"iteration":19,"passed_time":0.06429863557,"remaining_time":3.150633143},
{"learn":[9.338524633],"iteration":20,"passed_time":0.06464715403,"remaining_time":3.013788752},
{"learn":[9.170203312],"iteration":21,"passed_time":0.06492817699,"remaining_time":2.886352595},
{"learn":[9.010299969],"iteration":22,"passed_time":0.06523898963,"remaining_time":2.77123882},
{"learn":[8.843866678],"iteration":23,"passed_time":0.06558959128,"remaining_time":2.667310046},
{"learn":[8.690548059],"iteration":24,"passed_time":0.06592640219,"remaining_time":2.571129685},
{"learn":[8.555307687],"iteration":25,"passed_time":0.06621984099,"remaining_time":2.48069712},
{"learn":[8.413851302],"iteration":26,"passed_time":0.06652586228,"remaining_time":2.397394963},
{"learn":[8.29256019],"iteration":27,"passed_time":0.06688217189,"remaining_time":2.321766824},
{"learn":[8.162193833],"iteration":28,"passed_time":0.06717048603,"remaining_time":2.24905317},
{"learn":[8.040736294],"iteration":29,"passed_time":0.06753783657,"remaining_time":2.183723382},
{"learn":[7.921220278],"iteration":30,"passed_time":0.06781940115,"remaining_time":2.119903217},
{"learn":[7.809589039],"iteration":31,"passed_time":0.06812150604,"remaining_time":2.060675558},
{"learn":[7.699675801],"iteration":32,"passed_time":0.06841656973,"remaining_time":2.004812816},
{"learn":[7.60645267],"iteration":33,"passed_time":0.06864822097,"remaining_time":1.950417102},
{"learn":[7.498880302],"iteration":34,"passed_time":0.06897644912,"remaining_time":1.90177924},
{"learn":[7.401158744],"iteration":35,"passed_time":0.06926022189,"remaining_time":1.854634831},
{"learn":[7.306431077],"iteration":36,"passed_time":0.06951333004,"remaining_time":1.80922532},
{"learn":[7.223863468],"iteration":37,"passed_time":0.06980047758,"remaining_time":1.767054196},
{"learn":[7.143477682],"iteration":38,"passed_time":0.07006604324,"remaining_time":1.726499168},
{"learn":[7.062817131],"iteration":39,"passed_time":0.07033294213,"remaining_time":1.687990611},
{"learn":[6.990793435],"iteration":40,"passed_time":0.07056671823,"remaining_time":1.650572751},
{"learn":[6.931862224],"iteration":41,"passed_time":0.07082345114,"remaining_time":1.615449195},
{"learn":[6.858296558],"iteration":42,"passed_time":0.07110189093,"remaining_time":1.582430456},
{"learn":[6.786268161],"iteration":43,"passed_time":0.07140899549,"remaining_time":1.55152272},
{"learn":[6.717118549],"iteration":44,"passed_time":0.07173405718,"remaining_time":1.522356102},
{"learn":[6.652948106],"iteration":45,"passed_time":0.07200037278,"remaining_time":1.493225122},
{"learn":[6.589686076],"iteration":46,"passed_time":0.07226373024,"remaining_time":1.465262445},
{"learn":[6.531283097],"iteration":47,"passed_time":0.07248234069,"remaining_time":1.437566424},
{"learn":[6.471368031],"iteration":48,"passed_time":0.07272478288,"remaining_time":1.41145446},
{"learn":[6.416481395],"iteration":49,"passed_time":0.07299484823,"remaining_time":1.386902116},
{"learn":[6.369870822],"iteration":50,"passed_time":0.07327037155,"remaining_time":1.36340358},
{"learn":[6.325678067],"iteration":51,"passed_time":0.07354556156,"remaining_time":1.340792161},
{"learn":[6.275766122],"iteration":52,"passed_time":0.07392074492,"remaining_time":1.320810291},
{"learn":[6.224773967],"iteration":53,"passed_time":0.07422126657,"remaining_time":1.300246633},
{"learn":[6.182249254],"iteration":54,"passed_time":0.0744672502,"remaining_time":1.279482753},
{"learn":[6.139904173],"iteration":55,"passed_time":0.07475114796,"remaining_time":1.26009078},
{"learn":[6.100525536],"iteration":56,"passed_time":0.07505104466,"remaining_time":1.241633949},
{"learn":[6.062568564],"iteration":57,"passed_time":0.07536323221,"remaining_time":1.22400284},
{"learn":[6.030559288],"iteration":58,"passed_time":0.07560909084,"remaining_time":1.205900923},
{"learn":[5.997931376],"iteration":59,"passed_time":0.07591815359,"remaining_time":1.189384406},
{"learn":[5.964103835],"iteration":60,"passed_time":0.07623771565,"remaining_time":1.173560902},
{"learn":[5.933729724],"iteration":61,"passed_time":0.07648824064,"remaining_time":1.15719306},
{"learn":[5.901932711],"iteration":62,"passed_time":0.07679455357,"remaining_time":1.142166614},
{"learn":[5.873727795],"iteration":63,"passed_time":0.07703928728,"remaining_time":1.126699576},
{"learn":[5.846485734],"iteration":64,"passed_time":0.07727727143,"remaining_time":1.111603828},
{"learn":[5.820630862],"iteration":65,"passed_time":0.07764612188,"remaining_time":1.09881027},
{"learn":[5.793646238],"iteration":66,"passed_time":0.07797943302,"remaining_time":1.085892702},
{"learn":[5.765388646],"iteration":67,"passed_time":0.07826045597,"remaining_time":1.072628602},
{"learn":[5.747073912],"iteration":68,"passed_time":0.07862193191,"remaining_time":1.060826357},
{"learn":[5.722315217],"iteration":69,"passed_time":0.0789288698,"remaining_time":1.048626413},
{"learn":[5.699970599],"iteration":70,"passed_time":0.07920472644,"remaining_time":1.036354801},
{"learn":[5.682732647],"iteration":71,"passed_time":0.07952870486,"remaining_time":1.02503664},
{"learn":[5.663525791],"iteration":72,"passed_time":0.07983414286,"remaining_time":1.013784252},
{"learn":[5.642381613],"iteration":73,"passed_time":0.08023782432,"remaining_time":1.004057099},
{"learn":[5.621404779],"iteration":74,"passed_time":0.08059980022,"remaining_time":0.9940642027},
{"learn":[5.602460129],"iteration":75,"passed_time":0.08088407296,"remaining_time":0.9833800449},
{"learn":[5.587337574],"iteration":76,"passed_time":0.08115088852,"remaining_time":0.9727567546},
{"learn":[5.572393026],"iteration":77,"passed_time":0.0814220788,"remaining_time":0.9624507263},
{"learn":[5.558425806],"iteration":78,"passed_time":0.08168426968,"remaining_time":0.9522938275},
{"learn":[5.541518902],"iteration":79,"passed_time":0.08206141123,"remaining_time":0.9437062292},
{"learn":[5.526157283],"iteration":80,"passed_time":0.08240180524,"remaining_time":0.9349044322},
{"learn":[5.511746977],"iteration":81,"passed_time":0.0826882445,"remaining_time":0.9257049811},
{"learn":[5.504975022],"iteration":82,"passed_time":0.08278152995,"remaining_time":0.9145863008},
{"learn":[5.493980522],"iteration":83,"passed_time":0.0829971406,"remaining_time":0.905064057},
{"learn":[5.480745463],"iteration":84,"passed_time":0.08331624435,"remaining_time":0.8968748657},
{"learn":[5.464052013],"iteration":85,"passed_time":0.0836363897,"remaining_time":0.8888797696},
{"learn":[5.449143727],"iteration":86,"passed_time":0.08391870424,"remaining_time":0.8806641031},
{"learn":[5.438255432],"iteration":87,"passed_time":0.08417281232,"remaining_time":0.8723364186},
{"learn":[5.425927931],"iteration":88,"passed_time":0.08452983022,"remaining_time":0.865243543},
{"learn":[5.412331217],"iteration":89,"passed_time":0.08484218442,"remaining_time":0.8578487536},
{"learn":[5.400691499],"iteration":90,"passed_time":0.08508695979,"remaining_time":0.8499345763},
{"learn":[5.391618744],"iteration":91,"passed_time":0.08540493862,"remaining_time":0.8429096116},
{"learn":[5.380766572],"iteration":92,"passed_time":0.0856850033,"remaining_time":0.8356591182},
{"learn":[5.372207183],"iteration":93,"passed_time":0.08593890306,"remaining_time":0.8283047466},
{"learn":[5.362918837],"iteration":94,"passed_time":0.08630304549,"remaining_time":0.8221500649},
{"learn":[5.348292324],"iteration":95,"passed_time":0.08660202558,"remaining_time":0.8155024075},
{"learn":[5.339772295],"iteration":96,"passed_time":0.08692733725,"remaining_time":0.8092307788},
{"learn":[5.331515983],"iteration":97,"passed_time":0.08728552174,"remaining_time":0.8033830674},
{"learn":[5.323861644],"iteration":98,"passed_time":0.08761537478,"remaining_time":0.7973884108},
{"learn":[5.313277281],"iteration":99,"passed_time":0.08782765231,"remaining_time":0.7904488708},
{"learn":[5.30685627],"iteration":100,"passed_time":0.08804863759,"remaining_time":0.7837200515},
{"learn":[5.29652059],"iteration":101,"passed_time":0.08838194874,"remaining_time":0.7781077448},
{"learn":[5.288350766],"iteration":102,"passed_time":0.0887159265,"remaining_time":0.7726037482},
{"learn":[5.27993346],"iteration":103,"passed_time":0.08902878067,"remaining_time":0.7670171873},
{"learn":[5.271789139],"iteration":104,"passed_time":0.0893977561,"remaining_time":0.7620094449},
{"learn":[5.262684686],"iteration":105,"passed_time":0.08974673287,"remaining_time":0.7569205583},
{"learn":[5.251619772],"iteration":106,"passed_time":0.09010620893,"remaining_time":0.7520078932},
{"learn":[5.241012171],"iteration":107,"passed_time":0.09035965039,"remaining_time":0.7463037792},
{"learn":[5.232684032],"iteration":108,"passed_time":0.09062254955,"remaining_time":0.7407769876},
{"learn":[5.224267141],"iteration":109,"passed_time":0.0909797341,"remaining_time":0.7361087578},
{"learn":[5.216324968],"iteration":110,"passed_time":0.09126725663,"remaining_time":0.7309602806},
{"learn":[5.211102527],"iteration":111,"passed_time":0.0916166917,"remaining_time":0.7263894842},
{"learn":[5.206364257],"iteration":112,"passed_time":0.09194350327,"remaining_time":0.7217158177},
{"learn":[5.196937641],"iteration":113,"passed_time":0.09223856696,"remaining_time":0.7168716695},
{"learn":[5.190746047],"iteration":114,"passed_time":0.09254246339,"remaining_time":0.7121746096},
{"learn":[5.181885213],"iteration":115,"passed_time":0.0927946966,"remaining_time":0.7071595844},
{"learn":[5.178293568],"iteration":116,"passed_time":0.09300639083,"remaining_time":0.7019200265},
{"learn":[5.170991438],"iteration":117,"passed_time":0.09331620354,"remaining_time":0.6974990807},
{"learn":[5.166257212],"iteration":118,"passed_time":0.09362884939,"remaining_time":0.6931682043},
{"learn":[5.161421246],"iteration":119,"passed_time":0.09393203754,"remaining_time":0.6888349419},
{"learn":[5.158223542],"iteration":120,"passed_time":0.09424185024,"remaining_time":0.6846164162},
{"learn":[5.15470988],"iteration":121,"passed_time":0.09451704025,"remaining_time":0.6802127979},
{"learn":[5.146388143],"iteration":122,"passed_time":0.09489414014,"remaining_time":0.6766029342},
{"learn":[5.139529364],"iteration":123,"passed_time":0.09515033142,"remaining_time":0.672191051},
{"learn":[5.134276023],"iteration":124,"passed_time":0.09547239331,"remaining_time":0.6683067532},
{"learn":[5.128536065],"iteration":125,"passed_time":0.09575899923,"remaining_time":0.6642330581},
{"learn":[5.123300353],"iteration":126,"passed_time":0.09604418857,"remaining_time":0.6602092648},
{"learn":[5.116200518],"iteration":127,"passed_time":0.09635333466,"remaining_time":0.6564070923},
{"learn":[5.108728704],"iteration":128,"passed_time":0.09666577219,"remaining_time":0.652681299},
{"learn":[5.104075866],"iteration":129,"passed_time":0.0970430804,"remaining_time":0.6494421534},
{"learn":[5.100317606],"iteration":130,"passed_time":0.09736297577,"remaining_time":0.6458658469},
{"learn":[5.095814182],"iteration":131,"passed_time":0.09770549463,"remaining_time":0.6424876465},
{"learn":[5.092146915],"iteration":132,"passed_time":0.09801747386,"remaining_time":0.6389560138},
{"learn":[5.085258329],"iteration":133,"passed_time":0.09838407445,"remaining_time":0.6358254363},
{"learn":[5.079219421],"iteration":134,"passed_time":0.09869847018,"remaining_time":0.6324013089},
{"learn":[5.076476829],"iteration":135,"passed_time":0.09899540874,"remaining_time":0.6289120085},
{"learn":[5.072133867],"iteration":136,"passed_time":0.09933259463,"remaining_time":0.6257228406},
{"learn":[5.067031564],"iteration":137,"passed_time":0.09962445019,"remaining_time":0.6222918556},
{"learn":[5.061358312],"iteration":138,"passed_time":0.09992455521,"remaining_time":0.618957137},
{"learn":[5.056759124],"iteration":139,"passed_time":0.1002031617,"remaining_time":0.6155337074},
{"learn":[5.050254],"iteration":140,"passed_time":0.1004763518,"remaining_time":0.612121888},
{"learn":[5.048376474],"iteration":141,"passed_time":0.1006568398,"remaining_time":0.6081941446},
{"learn":[5.042603751],"iteration":142,"passed_time":0.1009220305,"remaining_time":0.6048264343},
{"learn":[5.037477349],"iteration":143,"passed_time":0.101204845,"remaining_time":0.6016065784},
{"learn":[5.03230489],"iteration":144,"passed_time":0.1014435374,"remaining_time":0.5981670654},
{"learn":[5.025976187],"iteration":145,"passed_time":0.1017634744,"remaining_time":0.5952466245},
{"learn":[5.01952451],"iteration":146,"passed_time":0.1020493721,"remaining_time":0.5921640434},
{"learn":[5.017569424],"iteration":147,"passed_time":0.1023375196,"remaining_time":0.5891322072},
{"learn":[5.008962367],"iteration":148,"passed_time":0.1025980022,"remaining_time":0.5859791938},
{"learn":[5.003880266],"iteration":149,"passed_time":0.1029690608,"remaining_time":0.5834913447},
{"learn":[4.996387564],"iteration":150,"passed_time":0.1032138362,"remaining_time":0.5803215029},
{"learn":[4.993361683],"iteration":151,"passed_time":0.1035434393,"remaining_time":0.577663398},
{"learn":[4.99005752],"iteration":152,"passed_time":0.1037872147,"remaining_time":0.5745605938},
{"learn":[4.986908764],"iteration":153,"passed_time":0.1040461558,"remaining_time":0.5715782325},
{"learn":[4.985207175],"iteration":154,"passed_time":0.1042764321,"remaining_time":0.5684747429},
{"learn":[4.979003494],"iteration":155,"passed_time":0.1045503722,"remaining_time":0.5656443215},
{"learn":[4.973142217],"iteration":156,"passed_time":0.1048527271,"remaining_time":0.5629990378},
{"learn":[4.967056696],"iteration":157,"passed_time":0.1051203759,"remaining_time":0.5601984591},
{"learn":[4.961460696],"iteration":158,"passed_time":0.1054397713,"remaining_time":0.5577034446},
{"learn":[4.954240363],"iteration":159,"passed_time":0.1057905396,"remaining_time":0.5554003331},
{"learn":[4.952320707],"iteration":160,"passed_time":0.1059929012,"remaining_time":0.5523480999},
{"learn":[4.948337777],"iteration":161,"passed_time":0.1063365866,"remaining_time":0.5500620962},
{"learn":[4.943228639],"iteration":162,"passed_time":0.1066443995,"remaining_time":0.5476157199},
{"learn":[4.938545759],"iteration":163,"passed_time":0.1070287489,"remaining_time":0.5455855735},
{"learn":[4.935330572],"iteration":164,"passed_time":0.1073596435,"remaining_time":0.5433048626},
{"learn":[4.932051543],"iteration":165,"passed_time":0.1077260358,"remaining_time":0.541225987},
{"learn":[4.928964153],"iteration":166,"passed_time":0.108022641,"remaining_time":0.5388195208},
{"learn":[4.922860227],"iteration":167,"passed_time":0.1084153232,"remaining_time":0.5369139817},
{"learn":[4.917668772],"iteration":168,"passed_time":0.1087457179,"remaining_time":0.5347200684},
{"learn":[4.910365386],"iteration":169,"passed_time":0.1091122768,"remaining_time":0.5327246456},
{"learn":[4.906457206],"iteration":170,"passed_time":0.1094698363,"remaining_time":0.5307046452},
{"learn":[4.901996508],"iteration":171,"passed_time":0.1097728162,"remaining_time":0.5284412313},
{"learn":[4.896816173],"iteration":172,"passed_time":0.1101235012,"remaining_time":0.5264285286},
{"learn":[4.891123132],"iteration":173,"passed_time":0.1103838172,"remaining_time":0.5240059366},
{"learn":[4.887630202],"iteration":174,"passed_time":0.1106751311,"remaining_time":0.5217541894},
{"learn":[4.885259712],"iteration":175,"passed_time":0.1109183232,"remaining_time":0.5192994224},
{"learn":[4.880659728],"iteration":176,"passed_time":0.1112288859,"remaining_time":0.5171828988},
{"learn":[4.877299723],"iteration":177,"passed_time":0.1115224913,"remaining_time":0.5150083589},
{"learn":[4.874038772],"iteration":178,"passed_time":0.1119045909,"remaining_time":0.5132607214},
{"learn":[4.86943698],"iteration":179,"passed_time":0.1122344856,"remaining_time":0.5112904344},
{"learn":[4.861268711],"iteration":180,"passed_time":0.1125806292,"remaining_time":0.5094117974},
{"learn":[4.858673056],"iteration":181,"passed_time":0.112909274,"remaining_time":0.5074713524},
{"learn":[4.854036207],"iteration":182,"passed_time":0.1131975465,"remaining_time":0.5053682813},
{"learn":[4.85130244],"iteration":183,"passed_time":0.1135198167,"remaining_time":0.5034357088},
{"learn":[4.847510084],"iteration":184,"passed_time":0.1138400454,"remaining_time":0.5015115512},
{"learn":[4.845691673],"iteration":185,"passed_time":0.1141361507,"remaining_time":0.4994990679},
{"learn":[4.842058646],"iteration":186,"passed_time":0.1145437485,"remaining_time":0.497989666},
{"learn":[4.838623675],"iteration":187,"passed_time":0.1148539779,"remaining_time":0.4960714363},
{"learn":[4.834602161],"iteration":188,"passed_time":0.115218037,"remaining_time":0.4944012062},
{"learn":[4.830858976],"iteration":189,"passed_time":0.1155430153,"remaining_time":0.4925781179},
{"learn":[4.827590511],"iteration":190,"passed_time":0.1158399122,"remaining_time":0.4906517748},
{"learn":[4.822246226],"iteration":191,"passed_time":0.1161295179,"remaining_time":0.4887117213},
{"learn":[4.816686395],"iteration":192,"passed_time":0.1164059579,"remaining_time":0.4867337202},
{"learn":[4.814797121],"iteration":193,"passed_time":0.116704563,"remaining_time":0.4848653493},
{"learn":[4.811639392],"iteration":194,"passed_time":0.1170204169,"remaining_time":0.4830842853},
{"learn":[4.804813432],"iteration":195,"passed_time":0.1173175638,"remaining_time":0.4812414353},
{"learn":[4.80251613],"iteration":196,"passed_time":0.1175663806,"remaining_time":0.4792172772},
{"learn":[4.800087884],"iteration":197,"passed_time":0.1178252384,"remaining_time":0.4772517231},
{"learn":[4.794773135],"iteration":198,"passed_time":0.1181427172,"remaining_time":0.4755392789},
{"learn":[4.791664833],"iteration":199,"passed_time":0.1184347394,"remaining_time":0.4737389578},
{"learn":[4.785989873],"iteration":200,"passed_time":0.1187363444,"remaining_time":0.471991737},
{"learn":[4.782387142],"iteration":201,"passed_time":0.1189728703,"remaining_time":0.4700017351},
{"learn":[4.778623704],"iteration":202,"passed_time":0.119236811,"remaining_time":0.4681366424},
{"learn":[4.775772178],"iteration":203,"passed_time":0.1195526233,"remaining_time":0.466489648},
{"learn":[4.77023101],"iteration":204,"passed_time":0.1198800182,"remaining_time":0.4649005584},
{"learn":[4.764496689],"iteration":205,"passed_time":0.1201951639,"remaining_time":0.4632765055},
{"learn":[4.763138716],"iteration":206,"passed_time":0.1205339747,"remaining_time":0.4617557581},
{"learn":[4.758053283],"iteration":207,"passed_time":0.1208757436,"remaining_time":0.460257639},
{"learn":[4.755063788],"iteration":208,"passed_time":0.1212571765,"remaining_time":0.4589207016},
{"learn":[4.752465267],"iteration":209,"passed_time":0.1215786135,"remaining_time":0.4573671649},
{"learn":[4.748067377],"iteration":210,"passed_time":0.1218787185,"remaining_time":0.4557455397},
{"learn":[4.744163298],"iteration":211,"passed_time":0.1222344448,"remaining_time":0.454343125},
{"learn":[4.736670896],"iteration":212,"passed_time":0.1225457991,"remaining_time":0.4527865909},
{"learn":[4.73349255],"iteration":213,"passed_time":0.1228597782,"remaining_time":0.4512513347},
{"learn":[4.731864595],"iteration":214,"passed_time":0.1231049285,"remaining_time":0.4494761343},
{"learn":[4.728398311],"iteration":215,"passed_time":0.1234464891,"remaining_time":0.4480650345},
{"learn":[4.723865975],"iteration":216,"passed_time":0.1238373797,"remaining_time":0.4468417895},
{"learn":[4.723483365],"iteration":217,"passed_time":0.1240947793,"remaining_time":0.4451473274},
{"learn":[4.72095416],"iteration":218,"passed_time":0.1243904679,"remaining_time":0.4436025362},
{"learn":[4.716173382],"iteration":219,"passed_time":0.1247696093,"remaining_time":0.4423649785},
{"learn":[4.710563974],"iteration":220,"passed_time":0.1250817969,"remaining_time":0.4408991845},
{"learn":[4.707160263],"iteration":221,"passed_time":0.1253541121,"remaining_time":0.4393040504},
{"learn":[4.70408351],"iteration":222,"passed_time":0.1256150114,"remaining_time":0.4376810037},
{"learn":[4.702501831],"iteration":223,"passed_time":0.125930532,"remaining_time":0.4362593431},
{"learn":[4.700269738],"iteration":224,"passed_time":0.1262273039,"remaining_time":0.4347829358},
{"learn":[4.695346302],"iteration":225,"passed_time":0.1265357001,"remaining_time":0.4333567781},
{"learn":[4.689769299],"iteration":226,"passed_time":0.1268586786,"remaining_time":0.4319901257},
{"learn":[4.687919514],"iteration":227,"passed_time":0.1271693662,"remaining_time":0.4305910119},
{"learn":[4.682982074],"iteration":228,"passed_time":0.1274551389,"remaining_time":0.4291175199},
{"learn":[4.679578702],"iteration":229,"passed_time":0.127757702,"remaining_time":0.4277105677},
{"learn":[4.675751423],"iteration":230,"passed_time":0.1280875967,"remaining_time":0.426404164},
{"learn":[4.672710726],"iteration":231,"passed_time":0.1283529124,"remaining_time":0.4248923997},
{"learn":[4.6690533],"iteration":232,"passed_time":0.1286408516,"remaining_time":0.4234658075},
{"learn":[4.667595702],"iteration":233,"passed_time":0.1289159166,"remaining_time":0.4220068039},
{"learn":[4.664241291],"iteration":234,"passed_time":0.1293462629,"remaining_time":0.4210633666},
{"learn":[4.662246999],"iteration":235,"passed_time":0.1296323689,"remaining_time":0.4196573298},
{"learn":[4.658668443],"iteration":236,"passed_time":0.1299427649,"remaining_time":0.4183389435},
{"learn":[4.658017572],"iteration":237,"passed_time":0.1302666183,"remaining_time":0.4170721141},
{"learn":[4.657656705],"iteration":238,"passed_time":0.130601846,"remaining_time":0.4158493925},
{"learn":[4.653242871],"iteration":239,"passed_time":0.1310533993,"remaining_time":0.415002431},
{"learn":[4.6507302],"iteration":240,"passed_time":0.1313142152,"remaining_time":0.4135580472},
{"learn":[4.647671336],"iteration":241,"passed_time":0.1316145286,"remaining_time":0.4122471598},
{"learn":[4.645506007],"iteration":242,"passed_time":0.1318828441,"remaining_time":0.4108449092},
{"learn":[4.641297906],"iteration":243,"passed_time":0.1321772828,"remaining_time":0.4095328925},
{"learn":[4.63798107],"iteration":244,"passed_time":0.1324253079,"remaining_time":0.408086153},
{"learn":[4.635062318],"iteration":245,"passed_time":0.1326972065,"remaining_time":0.4067223321},
{"learn":[4.631606017],"iteration":246,"passed_time":0.1329408569,"remaining_time":0.4052812359},
{"learn":[4.630215494],"iteration":247,"passed_time":0.1331956733,"remaining_time":0.4038836545},
{"learn":[4.62729814],"iteration":248,"passed_time":0.1334835291,"remaining_time":0.4025949011},
{"learn":[4.624691756],"iteration":249,"passed_time":0.1337295544,"remaining_time":0.4011886633},
{"learn":[4.621840053],"iteration":250,"passed_time":0.1340120773,"remaining_time":0.3999005812},
{"learn":[4.619602091],"iteration":251,"passed_time":0.1343327643,"remaining_time":0.3987337606},
{"learn":[4.613584029],"iteration":252,"passed_time":0.1347249881,"remaining_time":0.3977848464},
{"learn":[4.6119388],"iteration":253,"passed_time":0.1350567994,"remaining_time":0.3966628832},
{"learn":[4.60870702],"iteration":254,"passed_time":0.1353183653,"remaining_time":0.3953418908},
{"learn":[4.604771557],"iteration":255,"passed_time":0.1355556412,"remaining_time":0.3939585822},
{"learn":[4.604231277],"iteration":256,"passed_time":0.1358745366,"remaining_time":0.3928201584},
{"learn":[4.600750354],"iteration":257,"passed_time":0.136214139,"remaining_time":0.3917476401},
{"learn":[4.596488253],"iteration":258,"passed_time":0.13654895,"remaining_time":0.3906670733},
{"learn":[4.59470784],"iteration":259,"passed_time":0.1369820879,"remaining_time":0.3898720962},
{"learn":[4.588818005],"iteration":260,"passed_time":0.137295692,"remaining_time":0.3887414421},
{"learn":[4.585054174],"iteration":261,"passed_time":0.1375381342,"remaining_time":0.3874165764},
{"learn":[4.581471435],"iteration":262,"passed_time":0.1378479469,"remaining_time":0.3862887333},
{"learn":[4.577555199],"iteration":263,"passed_time":0.1381879242,"remaining_time":0.3852511828},
{"learn":[4.57457145],"iteration":264,"passed_time":0.1384566564,"remaining_time":0.3840212922},
{"learn":[4.573029224],"iteration":265,"passed_time":0.1387357628,"remaining_time":0.3828272552},
{"learn":[4.571326203],"iteration":266,"passed_time":0.1390342012,"remaining_time":0.3816931442},
{"learn":[4.571019224],"iteration":267,"passed_time":0.1393153908,"remaining_time":0.3805181571},
{"learn":[4.565766631],"iteration":268,"passed_time":0.1396487853,"remaining_time":0.3794916805},
{"learn":[4.563383471],"iteration":269,"passed_time":0.1399465988,"remaining_time":0.3783741376},
{"learn":[4.558165805],"iteration":270,"passed_time":0.1402715772,"remaining_time":0.3773357187},
{"learn":[4.55629209],"iteration":271,"passed_time":0.1405877645,"remaining_time":0.3762790167},
{"learn":[4.549383848],"iteration":272,"passed_time":0.1412515119,"remaining_time":0.3761532937},
{"learn":[4.546227503],"iteration":273,"passed_time":0.1416339448,"remaining_time":0.3752782625},
{"learn":[4.540620977],"iteration":274,"passed_time":0.1419371746,"remaining_time":0.3741980058},
{"learn":[4.532898237],"iteration":275,"passed_time":0.1422159894,"remaining_time":0.3730593345},
{"learn":[4.529757367],"iteration":276,"passed_time":0.1425867564,"remaining_time":0.3721668767},
{"learn":[4.52579294],"iteration":277,"passed_time":0.1428365314,"remaining_time":0.3709639413},
{"learn":[4.521572155],"iteration":278,"passed_time":0.1431707592,"remaining_time":0.3699860837},
{"learn":[4.518818099],"iteration":279,"passed_time":0.1434887796,"remaining_time":0.3689711477},
{"learn":[4.514012334],"iteration":280,"passed_time":0.1438565052,"remaining_time":0.3680883531},
{"learn":[4.508331416],"iteration":281,"passed_time":0.1442028988,"remaining_time":0.3671548983},
{"learn":[4.506038537],"iteration":282,"passed_time":0.1445636664,"remaining_time":0.3662620099},
{"learn":[4.505805643],"iteration":283,"passed_time":0.1448022755,"remaining_time":0.3650648918},
{"learn":[4.501550352],"iteration":284,"passed_time":0.1451159213,"remaining_time":0.3640627499},
{"learn":[4.494692643],"iteration":285,"passed_time":0.1453698211,"remaining_time":0.3629162666},
{"learn":[4.489330245],"iteration":286,"passed_time":0.1457136315,"remaining_time":0.3619993703},
{"learn":[4.484826955],"iteration":287,"passed_time":0.1460459427,"remaining_time":0.3610580251},
{"learn":[4.478285428],"iteration":288,"passed_time":0.146372171,"remaining_time":0.3601059293},
{"learn":[4.475311671],"iteration":289,"passed_time":0.1466497358,"remaining_time":0.3590390085},
{"learn":[4.471581298],"iteration":290,"passed_time":0.1469492992,"remaining_time":0.3580311105},
{"learn":[4.469164956],"iteration":291,"passed_time":0.1472932763,"remaining_time":0.3571357522},
{"learn":[4.462068024],"iteration":292,"passed_time":0.1476413365,"remaining_time":0.3562540099},
{"learn":[4.458540976],"iteration":293,"passed_time":0.1479676481,"remaining_time":0.355323672},
{"learn":[4.455757458],"iteration":294,"passed_time":0.1482410049,"remaining_time":0.3542708761},
{"learn":[4.453027414],"iteration":295,"passed_time":0.1485930648,"remaining_time":0.3534105325},
{"learn":[4.450659338],"iteration":296,"passed_time":0.1489794974,"remaining_time":0.352634972},
{"learn":[4.444696901],"iteration":297,"passed_time":0.1492414383,"remaining_time":0.3515687573},
{"learn":[4.442052813],"iteration":298,"passed_time":0.1495643335,"remaining_time":0.3506508286},
{"learn":[4.440036756],"iteration":299,"passed_time":0.1498150251,"remaining_time":0.3495683919},
{"learn":[4.435017051],"iteration":300,"passed_time":0.1500791742,"remaining_time":0.3485227334},
{"learn":[4.429962125],"iteration":301,"passed_time":0.1504131936,"remaining_time":0.3476437389},
{"learn":[4.427666256],"iteration":302,"passed_time":0.1507819191,"remaining_time":0.3468481768},
{"learn":[4.425030004],"iteration":303,"passed_time":0.1510342773,"remaining_time":0.3457890032},
{"learn":[4.422588771],"iteration":304,"passed_time":0.1513603389,"remaining_time":0.3449030673},
{"learn":[4.418936667],"iteration":305,"passed_time":0.1517358972,"remaining_time":0.3441330479},
{"learn":[4.416887976],"iteration":306,"passed_time":0.152033919,"remaining_time":0.3431905729},
{"learn":[4.413773354],"iteration":307,"passed_time":0.1523119838,"remaining_time":0.3422074442},
{"learn":[4.411129391],"iteration":308,"passed_time":0.1525913402,"remaining_time":0.3412317674},
{"learn":[4.40850819],"iteration":309,"passed_time":0.1529038194,"remaining_time":0.3403343078},
{"learn":[4.404880292],"iteration":310,"passed_time":0.1532987931,"remaining_time":0.3396233713},
{"learn":[4.404593827],"iteration":311,"passed_time":0.1536546861,"remaining_time":0.3388282822},
{"learn":[4.402139942],"iteration":312,"passed_time":0.153966457,"remaining_time":0.3379391565},
{"learn":[4.400284725],"iteration":313,"passed_time":0.1543093925,"remaining_time":0.3371217939},
{"learn":[4.395805521],"iteration":314,"passed_time":0.1546652855,"remaining_time":0.3363356208},
{"learn":[4.392838833],"iteration":315,"passed_time":0.1550245949,"remaining_time":0.3355595662},
{"learn":[4.389213061],"iteration":316,"passed_time":0.155323075,"remaining_time":0.3346550796},
{"learn":[4.3861981],"iteration":317,"passed_time":0.1555650589,"remaining_time":0.3336332396},
{"learn":[4.385054234],"iteration":318,"passed_time":0.1558099593,"remaining_time":0.332622515},
{"learn":[4.379364607],"iteration":319,"passed_time":0.1560981484,"remaining_time":0.3317085654},
{"learn":[4.378387619],"iteration":320,"passed_time":0.1564172522,"remaining_time":0.3308639073},
{"learn":[4.375816727],"iteration":321,"passed_time":0.1567309813,"remaining_time":0.3300111966},
{"learn":[4.374600202],"iteration":322,"passed_time":0.1570075462,"remaining_time":0.3290839281},
{"learn":[4.37098897],"iteration":323,"passed_time":0.1573653141,"remaining_time":0.3283300997},
{"learn":[4.367418484],"iteration":324,"passed_time":0.1577174156,"remaining_time":0.3275669401},
{"learn":[4.363584638],"iteration":325,"passed_time":0.1580682673,"remaining_time":0.3268037182},
{"learn":[4.360770706],"iteration":326,"passed_time":0.158372747,"remaining_time":0.3259475802},
{"learn":[4.358675808],"iteration":327,"passed_time":0.1587060581,"remaining_time":0.3251538752},
{"learn":[4.354228195],"iteration":328,"passed_time":0.159037911,"remaining_time":0.3243599948},
{"learn":[4.353773425],"iteration":329,"passed_time":0.1593759719,"remaining_time":0.3235815186},
{"learn":[4.351648009],"iteration":330,"passed_time":0.159703575,"remaining_time":0.3227845671},
{"learn":[4.348209927],"iteration":331,"passed_time":0.1601144227,"remaining_time":0.3221579348},
{"learn":[4.345852733],"iteration":332,"passed_time":0.1605149377,"remaining_time":0.3215119022},
{"learn":[4.34237339],"iteration":333,"passed_time":0.1608396244,"remaining_time":0.3207161373},
{"learn":[4.340814362],"iteration":334,"passed_time":0.1611417709,"remaining_time":0.3198784408},
{"learn":[4.339707068],"iteration":335,"passed_time":0.1614549584,"remaining_time":0.3190657512},
{"learn":[4.335430786],"iteration":336,"passed_time":0.1618020603,"remaining_time":0.3183227477},
{"learn":[4.33521887],"iteration":337,"passed_time":0.1621413294,"remaining_time":0.3175667457},
{"learn":[4.328507238],"iteration":338,"passed_time":0.1624291019,"remaining_time":0.3167127916},
{"learn":[4.326140732],"iteration":339,"passed_time":0.1627265404,"remaining_time":0.3158809314},
{"learn":[4.323785636],"iteration":340,"passed_time":0.1630035637,"remaining_time":0.315012752},
{"learn":[4.320632534],"iteration":341,"passed_time":0.1633066268,"remaining_time":0.3141981299},
{"learn":[4.31973724],"iteration":342,"passed_time":0.1635671928,"remaining_time":0.3133050894},
{"learn":[4.318000924],"iteration":343,"passed_time":0.1639117115,"remaining_time":0.312575822},
{"learn":[4.312713628],"iteration":344,"passed_time":0.1641766522,"remaining_time":0.311697702},
{"learn":[4.308220789],"iteration":345,"passed_time":0.1645147547,"remaining_time":0.310961415},
{"learn":[4.305890947],"iteration":346,"passed_time":0.1647744457,"remaining_time":0.3100798648},
{"learn":[4.305137856],"iteration":347,"passed_time":0.1650855084,"remaining_time":0.3092981364},
{"learn":[4.304787172],"iteration":348,"passed_time":0.1653338668,"remaining_time":0.3084021413},
{"learn":[4.30350134],"iteration":349,"passed_time":0.1656648031,"remaining_time":0.3076632058},
{"learn":[4.30293809],"iteration":350,"passed_time":0.1659576586,"remaining_time":0.3068561836},
{"learn":[4.299548459],"iteration":351,"passed_time":0.1662467227,"remaining_time":0.3060451032},
{"learn":[4.294768408],"iteration":352,"passed_time":0.1666188646,"remaining_time":0.3053892504},
{"learn":[4.294581479],"iteration":353,"passed_time":0.1669048456,"remaining_time":0.304577769},
{"learn":[4.292551604],"iteration":354,"passed_time":0.1672007842,"remaining_time":0.3037873403},
{"learn":[4.288628894],"iteration":355,"passed_time":0.1675121801,"remaining_time":0.3030276517},
{"learn":[4.287802767],"iteration":356,"passed_time":0.1678855719,"remaining_time":0.3023821366},
{"learn":[4.284566905],"iteration":357,"passed_time":0.1682574222,"remaining_time":0.3017353772},
{"learn":[4.27890232],"iteration":358,"passed_time":0.1685544441,"remaining_time":0.3009565422},
{"learn":[4.276938023],"iteration":359,"passed_time":0.1688105104,"remaining_time":0.300107574},
{"learn":[4.273425094],"iteration":360,"passed_time":0.1690714513,"remaining_time":0.2992705191},
{"learn":[4.269726505],"iteration":361,"passed_time":0.1694025543,"remaining_time":0.2985603028},
{"learn":[4.265565857],"iteration":362,"passed_time":0.169756864,"remaining_time":0.2978928991},
{"learn":[4.262117173],"iteration":363,"passed_time":0.1701255061,"remaining_time":0.297252258},
{"learn":[4.259185148],"iteration":364,"passed_time":0.1705054808,"remaining_time":0.2966328228},
{"learn":[4.257668507],"iteration":365,"passed_time":0.1708753312,"remaining_time":0.2959971584},
{"learn":[4.253432436],"iteration":366,"passed_time":0.1712055176,"remaining_time":0.2952945303},
{"learn":[4.250216667],"iteration":367,"passed_time":0.17156891,"remaining_time":0.2946509542},
{"learn":[4.24514828],"iteration":368,"passed_time":0.1718738481,"remaining_time":0.293908938},
{"learn":[4.244015772],"iteration":369,"passed_time":0.1721419135,"remaining_time":0.2931065014},
{"learn":[4.240329192],"iteration":370,"passed_time":0.1724602673,"remaining_time":0.2923922053},
{"learn":[4.236718014],"iteration":371,"passed_time":0.1728219099,"remaining_time":0.2917531168},
{"learn":[4.233495944],"iteration":372,"passed_time":0.1731898438,"remaining_time":0.2911260913},
{"learn":[4.230357491],"iteration":373,"passed_time":0.1735222383,"remaining_time":0.2904409657},
{"learn":[4.227381215],"iteration":374,"passed_time":0.1738960884,"remaining_time":0.289826814},
{"learn":[4.226169067],"iteration":375,"passed_time":0.1742139839,"remaining_time":0.2891210797},
{"learn":[4.225963861],"iteration":376,"passed_time":0.1745827927,"remaining_time":0.2885015381},
{"learn":[4.224346548],"iteration":377,"passed_time":0.1749922238,"remaining_time":0.2879501671},
{"learn":[4.222595381],"iteration":378,"passed_time":0.1753589077,"remaining_time":0.2873295031},
{"learn":[4.219700938],"iteration":379,"passed_time":0.1756663039,"remaining_time":0.2866134432},
{"learn":[4.216356207],"iteration":380,"passed_time":0.1759234951,"remaining_time":0.2858179618},
{"learn":[4.214326494],"iteration":381,"passed_time":0.1762326828,"remaining_time":0.2851094188},
{"learn":[4.212901398],"iteration":382,"passed_time":0.176556203,"remaining_time":0.2844260502},
{"learn":[4.211331091],"iteration":383,"passed_time":0.1768338928,"remaining_time":0.2836710364},
{"learn":[4.208624791],"iteration":384,"passed_time":0.1771066663,"remaining_time":0.2829106488},
{"learn":[4.204659106],"iteration":385,"passed_time":0.177466684,"remaining_time":0.2822915647},
{"learn":[4.202968852],"iteration":386,"passed_time":0.1777773717,"remaining_time":0.2815956817},
{"learn":[4.197261935],"iteration":387,"passed_time":0.1780237303,"remaining_time":0.2808003168},
{"learn":[4.196934403],"iteration":388,"passed_time":0.1782403825,"remaining_time":0.2799611149},
{"learn":[4.192479929],"iteration":389,"passed_time":0.1785608195,"remaining_time":0.2792874356},
{"learn":[4.190243116],"iteration":390,"passed_time":0.1788781317,"remaining_time":0.2786106962},
{"learn":[4.185852431],"iteration":391,"passed_time":0.1792524401,"remaining_time":0.2780241928},
{"learn":[4.180967944],"iteration":392,"passed_time":0.1795733354,"remaining_time":0.2773562712},
{"learn":[4.178283162],"iteration":393,"passed_time":0.1798589831,"remaining_time":0.2766358978},
{"learn":[4.176341157],"iteration":394,"passed_time":0.1802081265,"remaining_time":0.2760149785},
{"learn":[4.176041504],"iteration":395,"passed_time":0.1804731505,"remaining_time":0.2752671285},
{"learn":[4.175564513],"iteration":396,"passed_time":0.1807637145,"remaining_time":0.2745605034},
{"learn":[4.170830274],"iteration":397,"passed_time":0.1810792351,"remaining_time":0.2738937175},
{"learn":[4.167804808],"iteration":398,"passed_time":0.1814078799,"remaining_time":0.2732484608},
{"learn":[4.165860548],"iteration":399,"passed_time":0.1816305318,"remaining_time":0.2724457977},
{"learn":[4.160950571],"iteration":400,"passed_time":0.1818922227,"remaining_time":0.2717043426},
{"learn":[4.158544115],"iteration":401,"passed_time":0.1822913211,"remaining_time":0.2711696767},
{"learn":[4.154448767],"iteration":402,"passed_time":0.1825357215,"remaining_time":0.2704065155},
{"learn":[4.15197457],"iteration":403,"passed_time":0.1828729907,"remaining_time":0.2697829269},
{"learn":[4.149562679],"iteration":404,"passed_time":0.1831017672,"remaining_time":0.2690013616},
{"learn":[4.149327961],"iteration":405,"passed_time":0.1833689994,"remaining_time":0.2682787823},
{"learn":[4.147444889],"iteration":406,"passed_time":0.1835984008,"remaining_time":0.267503321},
{"learn":[4.147254809],"iteration":407,"passed_time":0.1838711326,"remaining_time":0.2667934081},
{"learn":[4.144589165],"iteration":408,"passed_time":0.1841739458,"remaining_time":0.2661291001},
{"learn":[4.141691034],"iteration":409,"passed_time":0.1844763006,"remaining_time":0.265465896},
{"learn":[4.138893468],"iteration":410,"passed_time":0.1847521156,"remaining_time":0.2647664138},
{"learn":[4.136964597],"iteration":411,"passed_time":0.1850195978,"remaining_time":0.2640570959},
{"learn":[4.133773523],"iteration":412,"passed_time":0.1852675813,"remaining_time":0.2633222039},
{"learn":[4.131363444],"iteration":413,"passed_time":0.1855747692,"remaining_time":0.2626734655},
{"learn":[4.130228592],"iteration":414,"passed_time":0.1858003791,"remaining_time":0.2619113778},
{"learn":[4.12884186],"iteration":415,"passed_time":0.1860346969,"remaining_time":0.2611640937},
{"learn":[4.12413494],"iteration":416,"passed_time":0.1863047622,"remaining_time":0.2604692479},
{"learn":[4.119422508],"iteration":417,"passed_time":0.1865288306,"remaining_time":0.259712391},
{"learn":[4.117038244],"iteration":418,"passed_time":0.1867602319,"remaining_time":0.2589682452},
{"learn":[4.116067631],"iteration":419,"passed_time":0.1869784674,"remaining_time":0.2582083597},
{"learn":[4.110343455],"iteration":420,"passed_time":0.1872054106,"remaining_time":0.2574630231},
{"learn":[4.105604544],"iteration":421,"passed_time":0.1874628101,"remaining_time":0.2567618584},
{"learn":[4.103390131],"iteration":422,"passed_time":0.1877509159,"remaining_time":0.2561046773},
{"learn":[4.096724402],"iteration":423,"passed_time":0.18799065,"remaining_time":0.2553835245},
{"learn":[4.093431279],"iteration":424,"passed_time":0.1882550074,"remaining_time":0.2546979512},
{"learn":[4.091412744],"iteration":425,"passed_time":0.1884981579,"remaining_time":0.2539857808},
{"learn":[4.091192901],"iteration":426,"passed_time":0.1887422249,"remaining_time":0.2532770372},
{"learn":[4.088994581],"iteration":427,"passed_time":0.1889856254,"remaining_time":0.2525695741},
{"learn":[4.087845355],"iteration":428,"passed_time":0.1892557324,"remaining_time":0.251899821},
{"learn":[4.083650279],"iteration":429,"passed_time":0.1894902168,"remaining_time":0.251184706},
{"learn":[4.079840652],"iteration":430,"passed_time":0.189723243,"remaining_time":0.2504698961},
{"learn":[4.075707828],"iteration":431,"passed_time":0.1900568041,"remaining_time":0.2498895017},
{"learn":[4.071345409],"iteration":432,"passed_time":0.1903032877,"remaining_time":0.249196222},
{"learn":[4.067460475],"iteration":433,"passed_time":0.1905254395,"remaining_time":0.2484732691},
{"learn":[4.064914749],"iteration":434,"passed_time":0.190778756,"remaining_time":0.2477930969},
{"learn":[4.063823175],"iteration":435,"passed_time":0.1910254479,"remaining_time":0.2471063134},
{"learn":[4.058898471],"iteration":436,"passed_time":0.1912766812,"remaining_time":0.2464273948},
{"learn":[4.054120355],"iteration":437,"passed_time":0.1915112072,"remaining_time":0.2457289919},
{"learn":[4.052715901],"iteration":438,"passed_time":0.1917296094,"remaining_time":0.2450120976},
{"learn":[4.052114167],"iteration":439,"passed_time":0.191985259,"remaining_time":0.2443448751},
{"learn":[4.051377267],"iteration":440,"passed_time":0.1922264929,"remaining_time":0.2436612462},
{"learn":[4.049275336],"iteration":441,"passed_time":0.1924885172,"remaining_time":0.2430058656},
{"learn":[4.047099198],"iteration":442,"passed_time":0.1927532079,"remaining_time":0.2423556135},
{"learn":[4.044348685],"iteration":443,"passed_time":0.1930209817,"remaining_time":0.2417109591},
{"learn":[4.042822379],"iteration":444,"passed_time":0.1932785479,"remaining_time":0.2410552676},
{"learn":[4.041258611],"iteration":445,"passed_time":0.1935334476,"remaining_time":0.2403980493},
{"learn":[4.040044254],"iteration":446,"passed_time":0.1937706401,"remaining_time":0.2397207248},
{"learn":[4.036860137],"iteration":447,"passed_time":0.1939799595,"remaining_time":0.2390110216},
{"learn":[4.036372284],"iteration":448,"passed_time":0.1942059862,"remaining_time":0.2383240498},
{"learn":[4.03368231],"iteration":449,"passed_time":0.194453553,"remaining_time":0.2376654537},
{"learn":[4.032439519],"iteration":450,"passed_time":0.1946829961,"remaining_time":0.2369866183},
{"learn":[4.032008634],"iteration":451,"passed_time":0.1949211885,"remaining_time":0.236320379},
{"learn":[4.030034932],"iteration":452,"passed_time":0.1951759216,"remaining_time":0.2356760024},
{"learn":[4.028173412],"iteration":453,"passed_time":0.1953916989,"remaining_time":0.2349864925},
{"learn":[4.023806097],"iteration":454,"passed_time":0.1956138924,"remaining_time":0.2343067503},
{"learn":[4.020239186],"iteration":455,"passed_time":0.1958343361,"remaining_time":0.2336269272},
{"learn":[4.017384838],"iteration":456,"passed_time":0.1960515299,"remaining_time":0.2329452533},
{"learn":[4.016468229],"iteration":457,"passed_time":0.1962588911,"remaining_time":0.2322539716},
{"learn":[4.014530169],"iteration":458,"passed_time":0.1964790848,"remaining_time":0.2315799235},
{"learn":[4.012884822],"iteration":459,"passed_time":0.1967123609,"remaining_time":0.2309232063},
{"learn":[4.008924707],"iteration":460,"passed_time":0.1969492618,"remaining_time":0.2302725643},
{"learn":[4.008286778],"iteration":461,"passed_time":0.197192579,"remaining_time":0.229631185},
{"learn":[4.006444202],"iteration":462,"passed_time":0.1974277716,"remaining_time":0.2289821023},
{"learn":[4.003284363],"iteration":463,"passed_time":0.1976654225,"remaining_time":0.2283376432},
{"learn":[3.999811484],"iteration":464,"passed_time":0.1979990253,"remaining_time":0.2278053302},
{"learn":[3.997483319],"iteration":465,"passed_time":0.1982597579,"remaining_time":0.2271903664},
{"learn":[3.99708333],"iteration":466,"passed_time":0.1985338647,"remaining_time":0.2265921839},
{"learn":[3.995860263],"iteration":467,"passed_time":0.1988219288,"remaining_time":0.2260112524},
{"learn":[3.994131111],"iteration":468,"passed_time":0.1990477471,"remaining_time":0.2253610953},
{"learn":[3.993125499],"iteration":469,"passed_time":0.1992780651,"remaining_time":0.2247178181},
{"learn":[3.992954084],"iteration":470,"passed_time":0.1994996754,"remaining_time":0.2240665144},
{"learn":[3.990635743],"iteration":471,"passed_time":0.1997277852,"remaining_time":0.2234243021},
{"learn":[3.986678254],"iteration":472,"passed_time":0.199935188,"remaining_time":0.2227607697},
{"learn":[3.986393291],"iteration":473,"passed_time":0.2001623396,"remaining_time":0.2221210772},
{"learn":[3.986152671],"iteration":474,"passed_time":0.2003751587,"remaining_time":0.2214672807},
{"learn":[3.985596662],"iteration":475,"passed_time":0.200615851,"remaining_time":0.2208460209},
{"learn":[3.983853457],"iteration":476,"passed_time":0.2008358364,"remaining_time":0.2202036529},
{"learn":[3.983263928],"iteration":477,"passed_time":0.2010982356,"remaining_time":0.2196093702},
{"learn":[3.980067202],"iteration":478,"passed_time":0.201356885,"remaining_time":0.2190123948},
{"learn":[3.978115407],"iteration":479,"passed_time":0.2015860364,"remaining_time":0.2183848728},
{"learn":[3.972661644],"iteration":480,"passed_time":0.2018286036,"remaining_time":0.2177734829},
{"learn":[3.969938254],"iteration":481,"passed_time":0.2020560885,"remaining_time":0.2171474146},
{"learn":[3.968211434],"iteration":482,"passed_time":0.2022751989,"remaining_time":0.2165140328},
{"learn":[3.966113368],"iteration":483,"passed_time":0.2025180577,"remaining_time":0.2159076814},
{"learn":[3.962246044],"iteration":484,"passed_time":0.2027759989,"remaining_time":0.2153188442},
{"learn":[3.961319703],"iteration":485,"passed_time":0.2030320652,"remaining_time":0.2147293858},
{"learn":[3.96078191],"iteration":486,"passed_time":0.2032763822,"remaining_time":0.2141289201},
{"learn":[3.958913633],"iteration":487,"passed_time":0.2035085751,"remaining_time":0.2135171936},
{"learn":[3.957428286],"iteration":488,"passed_time":0.2037317686,"remaining_time":0.212897615},
{"learn":[3.952641965],"iteration":489,"passed_time":0.2039595034,"remaining_time":0.2122843811},
{"learn":[3.951486786],"iteration":490,"passed_time":0.2041662397,"remaining_time":0.211650949},
{"learn":[3.94938344],"iteration":491,"passed_time":0.2043942245,"remaining_time":0.2110411911},
{"learn":[3.947297924],"iteration":492,"passed_time":0.204616543,"remaining_time":0.2104271548},
{"learn":[3.946284886],"iteration":493,"passed_time":0.2048393615,"remaining_time":0.2098152164},
{"learn":[3.943288204],"iteration":494,"passed_time":0.2050609301,"remaining_time":0.2092035751},
{"learn":[3.943076488],"iteration":495,"passed_time":0.2052800822,"remaining_time":0.2085910512},
{"learn":[3.942347078],"iteration":496,"passed_time":0.2055110251,"remaining_time":0.2079920435},
{"learn":[3.940251541],"iteration":497,"passed_time":0.2057401349,"remaining_time":0.2073926661},
{"learn":[3.939011019],"iteration":498,"passed_time":0.205943413,"remaining_time":0.2067688375},
{"learn":[3.938760512],"iteration":499,"passed_time":0.2061611902,"remaining_time":0.2061611902},
{"learn":[3.934522727],"iteration":500,"passed_time":0.2063898833,"remaining_time":0.2055659716},
{"learn":[3.930091193],"iteration":501,"passed_time":0.2066351169,"remaining_time":0.204988622},
{"learn":[3.927671752],"iteration":502,"passed_time":0.2068643933,"remaining_time":0.204396826},
{"learn":[3.927280041],"iteration":503,"passed_time":0.2071110436,"remaining_time":0.2038235667},
{"learn":[3.925987561],"iteration":504,"passed_time":0.2073718595,"remaining_time":0.2032654861},
{"learn":[3.921645957],"iteration":505,"passed_time":0.2075859286,"remaining_time":0.2026629422},
{"learn":[3.920333743],"iteration":506,"passed_time":0.2078416616,"remaining_time":0.2021024441},
{"learn":[3.918659461],"iteration":507,"passed_time":0.2080917283,"remaining_time":0.2015376581},
{"learn":[3.916124385],"iteration":508,"passed_time":0.208331879,"remaining_time":0.2009645434},
{"learn":[3.913849268],"iteration":509,"passed_time":0.2085841122,"remaining_time":0.2004043431},
{"learn":[3.912826119],"iteration":510,"passed_time":0.2088118887,"remaining_time":0.1998219443},
{"learn":[3.910034145],"iteration":511,"passed_time":0.2090894119,"remaining_time":0.1992883457},
{"learn":[3.90792379],"iteration":512,"passed_time":0.2093762261,"remaining_time":0.1987645655},
{"learn":[3.907823851],"iteration":513,"passed_time":0.2096344589,"remaining_time":0.1982146829},
{"learn":[3.904527401],"iteration":514,"passed_time":0.2098971914,"remaining_time":0.1976701706},
{"learn":[3.903378283],"iteration":515,"passed_time":0.210123718,"remaining_time":0.1970927897},
{"learn":[3.902170135],"iteration":516,"passed_time":0.2103572024,"remaining_time":0.1965232665},
{"learn":[3.899435429],"iteration":517,"passed_time":0.210609394,"remaining_time":0.1959724477},
{"learn":[3.897497505],"iteration":518,"passed_time":0.2108424618,"remaining_time":0.1954050561},
{"learn":[3.896426119],"iteration":519,"passed_time":0.2111114439,"remaining_time":0.1948721021},
{"learn":[3.896044669],"iteration":520,"passed_time":0.2113596774,"remaining_time":0.1943210853},
{"learn":[3.892795942],"iteration":521,"passed_time":0.2115691634,"remaining_time":0.1937357473},
{"learn":[3.892413888],"iteration":522,"passed_time":0.211790232,"remaining_time":0.1931624105},
{"learn":[3.891738985],"iteration":523,"passed_time":0.2120156754,"remaining_time":0.1925943921},
{"learn":[3.88822057],"iteration":524,"passed_time":0.2122444935,"remaining_time":0.1920307322},
{"learn":[3.883837053],"iteration":525,"passed_time":0.2124582292,"remaining_time":0.1914547541},
{"learn":[3.881769742],"iteration":526,"passed_time":0.2127078376,"remaining_time":0.1909123476},
{"learn":[3.880356898],"iteration":527,"passed_time":0.2129422803,"remaining_time":0.190357493},
{"learn":[3.879250273],"iteration":528,"passed_time":0.2131588492,"remaining_time":0.1897879357},
{"learn":[3.877174493],"iteration":529,"passed_time":0.2133736683,"remaining_time":0.1892181587},
{"learn":[3.875854201],"iteration":530,"passed_time":0.2136049862,"remaining_time":0.188664291},
{"learn":[3.873189396],"iteration":531,"passed_time":0.213853553,"remaining_time":0.1881268098},
{"learn":[3.871583368],"iteration":532,"passed_time":0.2141019115,"remaining_time":0.1875902301},
{"learn":[3.869622679],"iteration":533,"passed_time":0.2143463118,"remaining_time":0.1870512759},
{"learn":[3.866860164],"iteration":534,"passed_time":0.2145970452,"remaining_time":0.1865189271},
{"learn":[3.864498444],"iteration":535,"passed_time":0.2148299046,"remaining_time":0.1859721563},
{"learn":[3.861416322],"iteration":536,"passed_time":0.2150853876,"remaining_time":0.1854460605},
{"learn":[3.860265769],"iteration":537,"passed_time":0.2153271215,"remaining_time":0.1849091639},
{"learn":[3.859328725],"iteration":538,"passed_time":0.215581063,"remaining_time":0.1843838034},
{"learn":[3.858521278],"iteration":539,"passed_time":0.2158375042,"remaining_time":0.1838615777},
{"learn":[3.85599111],"iteration":540,"passed_time":0.2160855294,"remaining_time":0.1833331941},
{"learn":[3.852379816],"iteration":541,"passed_time":0.2163254301,"remaining_time":0.1827989797},
{"learn":[3.851327537],"iteration":542,"passed_time":0.2165495818,"remaining_time":0.1822525946},
{"learn":[3.847854898],"iteration":543,"passed_time":0.2168082313,"remaining_time":0.1817363115},
{"learn":[3.847083414],"iteration":544,"passed_time":0.2170228003,"remaining_time":0.1811841727},
{"learn":[3.845397429],"iteration":545,"passed_time":0.2172633676,"remaining_time":0.1806548881},
{"learn":[3.841933528],"iteration":546,"passed_time":0.2174888109,"remaining_time":0.1801141341},
{"learn":[3.840996474],"iteration":547,"passed_time":0.2177386276,"remaining_time":0.1795946345},
{"learn":[3.838355966],"iteration":548,"passed_time":0.217964196,"remaining_time":0.1790561974},
{"learn":[3.83342799],"iteration":549,"passed_time":0.2181965555,"remaining_time":0.1785244545},
{"learn":[3.828161535],"iteration":550,"passed_time":0.2184246236,"remaining_time":0.1779903013},
{"learn":[3.823502399],"iteration":551,"passed_time":0.2187374361,"remaining_time":0.1775260351},
{"learn":[3.820068862],"iteration":552,"passed_time":0.2189777535,"remaining_time":0.1770037175},
{"learn":[3.817951642],"iteration":553,"passed_time":0.2192184041,"remaining_time":0.1764826864},
{"learn":[3.815785958],"iteration":554,"passed_time":0.2194335981,"remaining_time":0.1759422544},
{"learn":[3.81503012],"iteration":555,"passed_time":0.2196632912,"remaining_time":0.1754145706},
{"learn":[3.813529315],"iteration":556,"passed_time":0.2198984005,"remaining_time":0.1748922647},
{"learn":[3.808881326],"iteration":557,"passed_time":0.2201138862,"remaining_time":0.1743554439},
{"learn":[3.808740434],"iteration":558,"passed_time":0.2203484955,"remaining_time":0.1738348596},
{"learn":[3.80714352],"iteration":559,"passed_time":0.2205576066,"remaining_time":0.1732952623},
{"learn":[3.80573346],"iteration":560,"passed_time":0.2208002155,"remaining_time":0.1727830563},
{"learn":[3.803370052],"iteration":561,"passed_time":0.2210741139,"remaining_time":0.1722961955},
{"learn":[3.803215211],"iteration":562,"passed_time":0.2212859331,"remaining_time":0.1717619055},
{"learn":[3.801309667],"iteration":563,"passed_time":0.2215335833,"remaining_time":0.171256458},
{"learn":[3.800003847],"iteration":564,"passed_time":0.2217689843,"remaining_time":0.1707424923},
{"learn":[3.798026138],"iteration":565,"passed_time":0.2220206759,"remaining_time":0.1702420024},
{"learn":[3.794745847],"iteration":566,"passed_time":0.2222666178,"remaining_time":0.1697379992},
{"learn":[3.794312041],"iteration":567,"passed_time":0.2224851866,"remaining_time":0.1692140856},
{"learn":[3.792205926],"iteration":568,"passed_time":0.2227015472,"remaining_time":0.1686895727},
{"learn":[3.788991061],"iteration":569,"passed_time":0.2229385731,"remaining_time":0.1681817306},
{"learn":[3.787391572],"iteration":570,"passed_time":0.2231757656,"remaining_time":0.1676749623},
{"learn":[3.7826445],"iteration":571,"passed_time":0.2234167496,"remaining_time":0.1671719735},
{"learn":[3.781700331],"iteration":572,"passed_time":0.2236726909,"remaining_time":0.1666810454},
{"learn":[3.780045374],"iteration":573,"passed_time":0.2239377566,"remaining_time":0.1661977078},
{"learn":[3.775462644],"iteration":574,"passed_time":0.2241830736,"remaining_time":0.1657005326},
{"learn":[3.773711943],"iteration":575,"passed_time":0.2244200995,"remaining_time":0.1651981288},
{"learn":[3.772415806],"iteration":576,"passed_time":0.2246785822,"remaining_time":0.1647123749},
{"learn":[3.770170875],"iteration":577,"passed_time":0.2249066504,"remaining_time":0.1642052015},
{"learn":[3.765166479],"iteration":578,"passed_time":0.2251892566,"remaining_time":0.1637386477},
{"learn":[3.763976102],"iteration":579,"passed_time":0.2254111168,"remaining_time":0.1632287398},
{"learn":[3.760761708],"iteration":580,"passed_time":0.2256466845,"remaining_time":0.1627297088},
{"learn":[3.758155662],"iteration":581,"passed_time":0.2258946263,"remaining_time":0.1622404704},
{"learn":[3.756844548],"iteration":582,"passed_time":0.2261032374,"remaining_time":0.1617239279},
{"learn":[3.753098923],"iteration":583,"passed_time":0.226323931,"remaining_time":0.1612170468},
{"learn":[3.751618946],"iteration":584,"passed_time":0.2265867052,"remaining_time":0.160740996},
{"learn":[3.751398464],"iteration":585,"passed_time":0.2268186481,"remaining_time":0.1602438913},
{"learn":[3.749920103],"iteration":586,"passed_time":0.2270426748,"remaining_time":0.1597421205},
{"learn":[3.748237465],"iteration":587,"passed_time":0.2272962413,"remaining_time":0.1592619922},
{"learn":[3.746021536],"iteration":588,"passed_time":0.2275234762,"remaining_time":0.1587642593},
{"learn":[3.74417648],"iteration":589,"passed_time":0.2277471696,"remaining_time":0.1582649823},
{"learn":[3.738788389],"iteration":590,"passed_time":0.2279650718,"remaining_time":0.15776263},
{"learn":[3.736021611],"iteration":591,"passed_time":0.2281990562,"remaining_time":0.1572723225},
{"learn":[3.734546151],"iteration":592,"passed_time":0.2284281243,"remaining_time":0.1567795052},
{"learn":[3.733527479],"iteration":593,"passed_time":0.2286983563,"remaining_time":0.1563157115},
{"learn":[3.733026392],"iteration":594,"passed_time":0.2289178,"remaining_time":0.1558179983},
{"learn":[3.730314752],"iteration":595,"passed_time":0.2291449932,"remaining_time":0.1553264719},
{"learn":[3.727342596],"iteration":596,"passed_time":0.2293812691,"remaining_time":0.1548419622},
{"learn":[3.725459604],"iteration":597,"passed_time":0.2296572091,"remaining_time":0.1543849466},
{"learn":[3.723158842],"iteration":598,"passed_time":0.2298809859,"remaining_time":0.1538936149},
{"learn":[3.722362756],"iteration":599,"passed_time":0.2300950133,"remaining_time":0.1533966755},
{"learn":[3.721443615],"iteration":600,"passed_time":0.2303282477,"remaining_time":0.152913429},
{"learn":[3.720743486],"iteration":601,"passed_time":0.2305504413,"remaining_time":0.1524237137},
{"learn":[3.720215334],"iteration":602,"passed_time":0.2307683434,"remaining_time":0.1519320603},
{"learn":[3.719436563],"iteration":603,"passed_time":0.2309892871,"remaining_time":0.1514433074},
{"learn":[3.715046574],"iteration":604,"passed_time":0.2312109806,"remaining_time":0.1509559295},
{"learn":[3.71443396],"iteration":605,"passed_time":0.2315002947,"remaining_time":0.1505133929},
{"learn":[3.712938941],"iteration":606,"passed_time":0.2317529862,"remaining_time":0.1500476501},
{"learn":[3.712814764],"iteration":607,"passed_time":0.231977013,"remaining_time":0.1495641268},
{"learn":[3.71235348],"iteration":608,"passed_time":0.2322354958,"remaining_time":0.1491035777},
{"learn":[3.711223749],"iteration":609,"passed_time":0.232467897,"remaining_time":0.1486270161},
{"learn":[3.710755648],"iteration":610,"passed_time":0.2327403371,"remaining_time":0.1481767449},
{"learn":[3.708668039],"iteration":611,"passed_time":0.2330023614,"remaining_time":0.1477204513},
{"learn":[3.705623591],"iteration":612,"passed_time":0.233218347,"remaining_time":0.1472357264},
{"learn":[3.704045802],"iteration":613,"passed_time":0.2334981617,"remaining_time":0.1467920039},
{"learn":[3.699915209],"iteration":614,"passed_time":0.2337512698,"remaining_time":0.1463320958},
{"learn":[3.696182221],"iteration":615,"passed_time":0.2340054196,"remaining_time":0.1458735083},
{"learn":[3.694263278],"iteration":616,"passed_time":0.2342282381,"remaining_time":0.1453961348},
{"learn":[3.693810229],"iteration":617,"passed_time":0.2344433904,"remaining_time":0.1449148465},
{"learn":[3.690900932],"iteration":618,"passed_time":0.2346593344,"remaining_time":0.1444349053},
{"learn":[3.688020895],"iteration":619,"passed_time":0.2349371492,"remaining_time":0.1439937366},
{"learn":[3.685491894],"iteration":620,"passed_time":0.2351916739,"remaining_time":0.1435388799},
{"learn":[3.684328128],"iteration":621,"passed_time":0.2354355327,"remaining_time":0.1430781855},
{"learn":[3.680640153],"iteration":622,"passed_time":0.2356935572,"remaining_time":0.1426267593},
{"learn":[3.678932783],"iteration":623,"passed_time":0.2359207921,"remaining_time":0.1421574003},
{"learn":[3.674167041],"iteration":624,"passed_time":0.2361493602,"remaining_time":0.1416896161},
{"learn":[3.672200976],"iteration":625,"passed_time":0.236382053,"remaining_time":0.1412250604},
{"learn":[3.670606604],"iteration":626,"passed_time":0.2366157874,"remaining_time":0.140761864},
{"learn":[3.665506042],"iteration":627,"passed_time":0.2368601878,"remaining_time":0.1403057164},
{"learn":[3.664214007],"iteration":628,"passed_time":0.2370983803,"remaining_time":0.1398465804},
{"learn":[3.66261643],"iteration":629,"passed_time":0.2373531967,"remaining_time":0.1393979092},
{"learn":[3.662118449],"iteration":630,"passed_time":0.2375848063,"remaining_time":0.1389362813},
{"learn":[3.660871366],"iteration":631,"passed_time":0.2378055416,"remaining_time":0.1384690495},
{"learn":[3.656695243],"iteration":632,"passed_time":0.238064191,"remaining_time":0.1380245784},
{"learn":[3.654497801],"iteration":633,"passed_time":0.2383572965,"remaining_time":0.1376005844},
{"learn":[3.654189134],"iteration":634,"passed_time":0.238594364,"remaining_time":0.1371447919},
{"learn":[3.653957699],"iteration":635,"passed_time":0.238829765,"remaining_time":0.1366887334},
{"learn":[3.651920725],"iteration":636,"passed_time":0.2390536668,"remaining_time":0.1362268148},
{"learn":[3.65106705],"iteration":637,"passed_time":0.2393198991,"remaining_time":0.1357896606},
{"learn":[3.650612844],"iteration":638,"passed_time":0.2395572166,"remaining_time":0.1353367061},
{"learn":[3.649884732],"iteration":639,"passed_time":0.2397744105,"remaining_time":0.1348731059},
{"learn":[3.646276182],"iteration":640,"passed_time":0.2400138112,"remaining_time":0.1344227117},
{"learn":[3.645808194],"iteration":641,"passed_time":0.2402280886,"remaining_time":0.1339589653},
{"learn":[3.645042989],"iteration":642,"passed_time":0.240462948,"remaining_time":0.1335074221},
{"learn":[3.639864499],"iteration":643,"passed_time":0.2407650945,"remaining_time":0.1330937479},
{"learn":[3.637318478],"iteration":644,"passed_time":0.2410003289,"remaining_time":0.1326435918},
{"learn":[3.636344905],"iteration":645,"passed_time":0.2412391879,"remaining_time":0.1321960875},
{"learn":[3.634754643],"iteration":646,"passed_time":0.2414919211,"remaining_time":0.1317567978},
{"learn":[3.630724975],"iteration":647,"passed_time":0.2417291553,"remaining_time":0.1313096646},
{"learn":[3.629408252],"iteration":648,"passed_time":0.2419570152,"remaining_time":0.1308581083},
{"learn":[3.62790646],"iteration":649,"passed_time":0.2421787921,"remaining_time":0.130403965},
{"learn":[3.627388973],"iteration":650,"passed_time":0.2424746474,"remaining_time":0.1299902487},
{"learn":[3.625163557],"iteration":651,"passed_time":0.2427408796,"remaining_time":0.129561083},
{"learn":[3.623701985],"iteration":652,"passed_time":0.2430311103,"remaining_time":0.1291451689},
{"learn":[3.622342639],"iteration":653,"passed_time":0.2432463876,"remaining_time":0.1286899849},
{"learn":[3.621130639],"iteration":654,"passed_time":0.2434738308,"remaining_time":0.1282419414},
{"learn":[3.619125665],"iteration":655,"passed_time":0.2437198561,"remaining_time":0.1278043148},
{"learn":[3.618878783],"iteration":656,"passed_time":0.243957382,"remaining_time":0.1273628341},
{"learn":[3.616207429],"iteration":657,"passed_time":0.2442322803,"remaining_time":0.126941398},
{"learn":[3.61206486],"iteration":658,"passed_time":0.2444585153,"remaining_time":0.1264952257},
{"learn":[3.611955873],"iteration":659,"passed_time":0.244682167,"remaining_time":0.1260483891},
{"learn":[3.610713743],"iteration":660,"passed_time":0.2449469411,"remaining_time":0.1256233177},
{"learn":[3.610044025],"iteration":661,"passed_time":0.2451683013,"remaining_time":0.1251765647},
{"learn":[3.607342669],"iteration":662,"passed_time":0.2454012858,"remaining_time":0.1247364002},
{"learn":[3.602510618],"iteration":663,"passed_time":0.2456757259,"remaining_time":0.1243178372},
{"learn":[3.600492392],"iteration":664,"passed_time":0.2459321671,"remaining_time":0.1238906406},
{"learn":[3.597171065],"iteration":665,"passed_time":0.2461973578,"remaining_time":0.1234683446},
{"learn":[3.594358798],"iteration":666,"passed_time":0.2464383834,"remaining_time":0.1230344553},
{"learn":[3.593945251],"iteration":667,"passed_time":0.2466512443,"remaining_time":0.1225871454},
{"learn":[3.593607748],"iteration":668,"passed_time":0.2468591888,"remaining_time":0.1221381039},
{"learn":[3.592238714],"iteration":669,"passed_time":0.2471055474,"remaining_time":0.1217087024},
{"learn":[3.590144654],"iteration":670,"passed_time":0.2473266576,"remaining_time":0.121267467},
{"learn":[3.587151536],"iteration":671,"passed_time":0.2475532675,"remaining_time":0.1208295711},
{"learn":[3.586070865],"iteration":672,"passed_time":0.2477745861,"remaining_time":0.120389732},
{"learn":[3.585102746],"iteration":673,"passed_time":0.2480356938,"remaining_time":0.1199697866},
{"learn":[3.584362847],"iteration":674,"passed_time":0.2482635536,"remaining_time":0.1195343036},
{"learn":[3.581407561],"iteration":675,"passed_time":0.248512537,"remaining_time":0.1191095592},
{"learn":[3.57919422],"iteration":676,"passed_time":0.2487470631,"remaining_time":0.1186784363},
{"learn":[3.577632204],"iteration":677,"passed_time":0.2489994213,"remaining_time":0.1182563623},
{"learn":[3.573911195],"iteration":678,"passed_time":0.2492374471,"remaining_time":0.1178280125},
{"learn":[3.573408216],"iteration":679,"passed_time":0.2494733897,"remaining_time":0.1173992422},
{"learn":[3.571076482],"iteration":680,"passed_time":0.2497509129,"remaining_time":0.1169905157},
{"learn":[3.568177107],"iteration":681,"passed_time":0.2499966465,"remaining_time":0.1165673513},
{"learn":[3.564824621],"iteration":682,"passed_time":0.2502575875,"remaining_time":0.1161517646},
{"learn":[3.562475026],"iteration":683,"passed_time":0.2504839891,"remaining_time":0.1157206733},
{"learn":[3.561226889],"iteration":684,"passed_time":0.250706141,"remaining_time":0.1152882254},
{"learn":[3.559383467],"iteration":685,"passed_time":0.250935209,"remaining_time":0.1148595563},
{"learn":[3.555209766],"iteration":686,"passed_time":0.2511873589,"remaining_time":0.1144419845},
{"learn":[3.55345383],"iteration":687,"passed_time":0.2514161354,"remaining_time":0.1140142939},
{"learn":[3.552300968],"iteration":688,"passed_time":0.2516425786,"remaining_time":0.1135861276},
{"learn":[3.551253986],"iteration":689,"passed_time":0.2518605641,"remaining_time":0.1131547462},
{"learn":[3.549807725],"iteration":690,"passed_time":0.2520993399,"remaining_time":0.1127332793},
{"learn":[3.547992926],"iteration":691,"passed_time":0.2523368657,"remaining_time":0.1123117842},
{"learn":[3.545438607],"iteration":692,"passed_time":0.252602348,"remaining_time":0.1119032047},
{"learn":[3.543313763],"iteration":693,"passed_time":0.2528516231,"remaining_time":0.1114878915},
{"learn":[3.542962896],"iteration":694,"passed_time":0.2530673171,"remaining_time":0.111058319},
{"learn":[3.539800465],"iteration":695,"passed_time":0.2533254249,"remaining_time":0.1106478867},
{"learn":[3.53953187],"iteration":696,"passed_time":0.25354966,"remaining_time":0.1102231664},
{"learn":[3.536332425],"iteration":697,"passed_time":0.2537703953,"remaining_time":0.1097975063},
{"learn":[3.534993327],"iteration":698,"passed_time":0.2540178371,"remaining_time":0.1093839327},
{"learn":[3.531637011],"iteration":699,"passed_time":0.2543077345,"remaining_time":0.1089890291},
{"learn":[3.531040284],"iteration":700,"passed_time":0.2545556347,"remaining_time":0.1085765118},
{"learn":[3.529973872],"iteration":701,"passed_time":0.2548311996,"remaining_time":0.1081762073},
{"learn":[3.527325183],"iteration":702,"passed_time":0.2550574762,"remaining_time":0.1077554345},
{"learn":[3.527200815],"iteration":703,"passed_time":0.2552719203,"remaining_time":0.1073302392},
{"learn":[3.523459911],"iteration":704,"passed_time":0.255536611,"remaining_time":0.106926667},
{"learn":[3.522729934],"iteration":705,"passed_time":0.2557781366,"remaining_time":0.1065138416},
{"learn":[3.522260582],"iteration":706,"passed_time":0.2560179956,"remaining_time":0.1061008101},
{"learn":[3.518641591],"iteration":707,"passed_time":0.2562591046,"remaining_time":0.1056887832},
{"learn":[3.516856405],"iteration":708,"passed_time":0.2565299615,"remaining_time":0.1052894482},
{"learn":[3.515083413],"iteration":709,"passed_time":0.2567713621,"remaining_time":0.1048784437},
{"learn":[3.514671214],"iteration":710,"passed_time":0.2569940973,"remaining_time":0.1044603293},
{"learn":[3.512617621],"iteration":711,"passed_time":0.2572410392,"remaining_time":0.1040525552},
{"learn":[3.510747971],"iteration":712,"passed_time":0.2574758152,"remaining_time":0.1036403352},
{"learn":[3.508149266],"iteration":713,"passed_time":0.2577120078,"remaining_time":0.1032291796},
{"learn":[3.504557165],"iteration":714,"passed_time":0.2579307849,"remaining_time":0.1028115716},
{"learn":[3.501367208],"iteration":715,"passed_time":0.25818006,"remaining_time":0.102406616},
{"learn":[3.497593362],"iteration":716,"passed_time":0.2584163359,"remaining_time":0.1019969638},
{"learn":[3.496291169],"iteration":717,"passed_time":0.2586556533,"remaining_time":0.1015889892},
{"learn":[3.49330374],"iteration":718,"passed_time":0.258890346,"remaining_time":0.1011796763},
{"learn":[3.490044385],"iteration":719,"passed_time":0.2591435375,"remaining_time":0.1007780424},
{"learn":[3.488891789],"iteration":720,"passed_time":0.2593649811,"remaining_time":0.100364535},
{"learn":[3.486869081],"iteration":721,"passed_time":0.2596035902,"remaining_time":0.09995816909},
{"learn":[3.486303638],"iteration":722,"passed_time":0.2598510737,"remaining_time":0.09955566726},
{"learn":[3.486035862],"iteration":723,"passed_time":0.2600744339,"remaining_time":0.09914439744},
{"learn":[3.482668951],"iteration":724,"passed_time":0.2603053768,"remaining_time":0.09873652224},
{"learn":[3.47820549],"iteration":725,"passed_time":0.2605461525,"remaining_time":0.09833284542},
{"learn":[3.474392283],"iteration":726,"passed_time":0.2607812618,"remaining_time":0.09792748896},
{"learn":[3.472268163],"iteration":727,"passed_time":0.261024204,"remaining_time":0.09752552676},
{"learn":[3.471209164],"iteration":728,"passed_time":0.2613146846,"remaining_time":0.09714167289},
{"learn":[3.470049971],"iteration":729,"passed_time":0.2615292953,"remaining_time":0.09673001334},
{"learn":[3.469078654],"iteration":730,"passed_time":0.261779862,"remaining_time":0.09633212431},
{"learn":[3.468643292],"iteration":731,"passed_time":0.2620196794,"remaining_time":0.09593070228},
{"learn":[3.468134848],"iteration":732,"passed_time":0.2622719542,"remaining_time":0.0955342589},
{"learn":[3.467820182],"iteration":733,"passed_time":0.2625089384,"remaining_time":0.09513266707},
{"learn":[3.465776156],"iteration":734,"passed_time":0.2627249657,"remaining_time":0.09472396723},
{"learn":[3.463037608],"iteration":735,"passed_time":0.262951034,"remaining_time":0.09431939263},
{"learn":[3.45965637],"iteration":736,"passed_time":0.2631553954,"remaining_time":0.0939075563},
{"learn":[3.457275091],"iteration":737,"passed_time":0.2634301271,"remaining_time":0.09352126464},
{"learn":[3.455522955],"iteration":738,"passed_time":0.2636455711,"remaining_time":0.09311433567},
{"learn":[3.451270508],"iteration":739,"passed_time":0.2638648898,"remaining_time":0.09270928562},
{"learn":[3.450978947],"iteration":740,"passed_time":0.2640833336,"remaining_time":0.09230443105},
{"learn":[3.450608492],"iteration":741,"passed_time":0.2643040273,"remaining_time":0.09190086123},
{"learn":[3.448122004],"iteration":742,"passed_time":0.2645623434,"remaining_time":0.09151079711},
{"learn":[3.445646714],"iteration":743,"passed_time":0.2647883283,"remaining_time":0.09110996244},
{"learn":[3.44411263],"iteration":744,"passed_time":0.2650066888,"remaining_time":0.09070698744},
{"learn":[3.443264164],"iteration":745,"passed_time":0.2652321321,"remaining_time":0.09030691898},
{"learn":[3.439521363],"iteration":746,"passed_time":0.2654904483,"remaining_time":0.08991845169},
{"learn":[3.436809225],"iteration":747,"passed_time":0.2657177665,"remaining_time":0.08951988924},
{"learn":[3.435509465],"iteration":748,"passed_time":0.265934877,"remaining_time":0.08911836332},
{"learn":[3.434450277],"iteration":749,"passed_time":0.2661498627,"remaining_time":0.0887166209},
{"learn":[3.431786753],"iteration":750,"passed_time":0.2663765976,"remaining_time":0.08831927137},
{"learn":[3.430150302],"iteration":751,"passed_time":0.2666150817,"remaining_time":0.08792625035},
{"learn":[3.42696281],"iteration":752,"passed_time":0.2668413167,"remaining_time":0.0875296218},
{"learn":[3.426870334],"iteration":753,"passed_time":0.2670537192,"remaining_time":0.08712893225},
{"learn":[3.425200309],"iteration":754,"passed_time":0.2673174933,"remaining_time":0.08674541173},
{"learn":[3.423383783],"iteration":755,"passed_time":0.2675448531,"remaining_time":0.08635045525},
{"learn":[3.422752979],"iteration":756,"passed_time":0.267802961,"remaining_time":0.08596581177},
{"learn":[3.420845924],"iteration":757,"passed_time":0.2680450282,"remaining_time":0.08557638103},
{"learn":[3.418917862],"iteration":758,"passed_time":0.2683085523,"remaining_time":0.08519415165},
{"learn":[3.417095735],"iteration":759,"passed_time":0.2685177467,"remaining_time":0.08479507791},
{"learn":[3.414391848],"iteration":760,"passed_time":0.2687664801,"remaining_time":0.08440892083},
{"learn":[3.41426711],"iteration":761,"passed_time":0.2690282544,"remaining_time":0.08402719756},
{"learn":[3.411976013],"iteration":762,"passed_time":0.2692561142,"remaining_time":0.08363525435},
{"learn":[3.408614844],"iteration":763,"passed_time":0.2694759746,"remaining_time":0.08324126963},
{"learn":[3.407906721],"iteration":764,"passed_time":0.2697012929,"remaining_time":0.08284941677},
{"learn":[3.407494015],"iteration":765,"passed_time":0.2699279028,"remaining_time":0.08245839329},
{"learn":[3.406287128],"iteration":766,"passed_time":0.2701710533,"remaining_time":0.08207282323},
{"learn":[3.404600442],"iteration":767,"passed_time":0.2703955383,"remaining_time":0.08168198554},
{"learn":[3.404012662],"iteration":768,"passed_time":0.2706270229,"remaining_time":0.08129368309},
{"learn":[3.400398762],"iteration":769,"passed_time":0.270875548,"remaining_time":0.08091087799},
{"learn":[3.399737714],"iteration":770,"passed_time":0.2711338225,"remaining_time":0.08053131693},
{"learn":[3.399185251],"iteration":771,"passed_time":0.2713608491,"remaining_time":0.08014284144},
{"learn":[3.397245411],"iteration":772,"passed_time":0.2715805428,"remaining_time":0.07975263028},
{"learn":[3.396229831],"iteration":773,"passed_time":0.2717961951,"remaining_time":0.0793616797},
{"learn":[3.394002836],"iteration":774,"passed_time":0.2720795929,"remaining_time":0.07899084955},
{"learn":[3.389617243],"iteration":775,"passed_time":0.2723675737,"remaining_time":0.07862156767},
{"learn":[3.385426488],"iteration":776,"passed_time":0.2726033913,"remaining_time":0.07823752416},
{"learn":[3.385072258],"iteration":777,"passed_time":0.2728151272,"remaining_time":0.07784699004},
{"learn":[3.383842366],"iteration":778,"passed_time":0.2730621108,"remaining_time":0.07746691462},
{"learn":[3.380110746],"iteration":779,"passed_time":0.2733122608,"remaining_time":0.07708807356},
{"learn":[3.378595218],"iteration":780,"passed_time":0.2735512866,"remaining_time":0.07670644271},
{"learn":[3.377371219],"iteration":781,"passed_time":0.2737789797,"remaining_time":0.07632201737},
{"learn":[3.375814782],"iteration":782,"passed_time":0.2740341294,"remaining_time":0.07594560164},
{"learn":[3.374195887],"iteration":783,"passed_time":0.274250115,"remaining_time":0.07555870516},
{"learn":[3.373704309],"iteration":784,"passed_time":0.2744598927,"remaining_time":0.07517054387},
{"learn":[3.372971757],"iteration":785,"passed_time":0.2746542548,"remaining_time":0.07477863934},
{"learn":[3.371565136],"iteration":786,"passed_time":0.2748956137,"remaining_time":0.07439995645},
{"learn":[3.3700309],"iteration":787,"passed_time":0.2751289732,"remaining_time":0.07401946994},
{"learn":[3.368186663],"iteration":788,"passed_time":0.2753532499,"remaining_time":0.07363692742},
{"learn":[3.366710398],"iteration":789,"passed_time":0.2755654858,"remaining_time":0.07325158483},
{"learn":[3.364598042],"iteration":790,"passed_time":0.2757997202,"remaining_time":0.07287249244},
{"learn":[3.36348442],"iteration":791,"passed_time":0.2760151642,"remaining_time":0.072488831},
{"learn":[3.362001759],"iteration":792,"passed_time":0.2762493153,"remaining_time":0.072110477},
{"learn":[3.361580401],"iteration":793,"passed_time":0.2764795499,"remaining_time":0.07173147013},
{"learn":[3.359543675],"iteration":794,"passed_time":0.2767611978,"remaining_time":0.07136609504},
{"learn":[3.35766119],"iteration":795,"passed_time":0.276999432,"remaining_time":0.07098980418},
{"learn":[3.354592969],"iteration":796,"passed_time":0.277250082,"remaining_time":0.07061702213},
{"learn":[3.350985986],"iteration":797,"passed_time":0.2774552766,"remaining_time":0.07023303995},
{"learn":[3.349589624],"iteration":798,"passed_time":0.2776819282,"remaining_time":0.06985490309},
{"learn":[3.349110856],"iteration":799,"passed_time":0.2778919142,"remaining_time":0.06947297856},
{"learn":[3.345315441],"iteration":800,"passed_time":0.2781566049,"remaining_time":0.06910507413},
{"learn":[3.34397474],"iteration":801,"passed_time":0.278376382,"remaining_time":0.06872633869},
{"learn":[3.343800902],"iteration":802,"passed_time":0.2785969506,"remaining_time":0.06834819336},
{"learn":[3.342329465],"iteration":803,"passed_time":0.2788231022,"remaining_time":0.06797180104},
{"learn":[3.34220347],"iteration":804,"passed_time":0.2790602531,"remaining_time":0.0675984464},
{"learn":[3.341279219],"iteration":805,"passed_time":0.2792830299,"remaining_time":0.06722196998},
{"learn":[3.337329521],"iteration":806,"passed_time":0.2795165561,"remaining_time":0.06684844525},
{"learn":[3.336708453],"iteration":807,"passed_time":0.2797601232,"remaining_time":0.06647765303},
{"learn":[3.333252703],"iteration":808,"passed_time":0.2799650679,"remaining_time":0.06609805681},
{"learn":[3.332186769],"iteration":809,"passed_time":0.2802469241,"remaining_time":0.06573693281},
{"learn":[3.330594851],"iteration":810,"passed_time":0.2804841166,"remaining_time":0.06536559561},
{"learn":[3.327867442],"iteration":811,"passed_time":0.2807198509,"remaining_time":0.0649942512},
{"learn":[3.327563111],"iteration":812,"passed_time":0.2809431277,"remaining_time":0.06462037501},
{"learn":[3.326308994],"iteration":813,"passed_time":0.2811549053,"remaining_time":0.06424424126},
{"learn":[3.326249879],"iteration":814,"passed_time":0.2813509339,"remaining_time":0.06386493592},
{"learn":[3.322336238],"iteration":815,"passed_time":0.2815672528,"remaining_time":0.06349065505},
{"learn":[3.320491154],"iteration":816,"passed_time":0.2817829468,"remaining_time":0.06311662089},
{"learn":[3.320434271],"iteration":817,"passed_time":0.281990183,"remaining_time":0.06274109207},
{"learn":[3.319609638],"iteration":818,"passed_time":0.2822094184,"remaining_time":0.06236862605},
{"learn":[3.316182682],"iteration":819,"passed_time":0.2824812337,"remaining_time":0.06200807568},
{"learn":[3.313126612],"iteration":820,"passed_time":0.2827329252,"remaining_time":0.06164335398},
{"learn":[3.311222803],"iteration":821,"passed_time":0.2829480776,"remaining_time":0.0612709949},
{"learn":[3.309627335],"iteration":822,"passed_time":0.2831994775,"remaining_time":0.06090681351},
{"learn":[3.307974895],"iteration":823,"passed_time":0.2834200462,"remaining_time":0.06053632054},
{"learn":[3.307321505],"iteration":824,"passed_time":0.2836389066,"remaining_time":0.06016582867},
{"learn":[3.306759087],"iteration":825,"passed_time":0.2838686829,"remaining_time":0.05979800343},
{"learn":[3.30484037],"iteration":826,"passed_time":0.2840850852,"remaining_time":0.05942771432},
{"learn":[3.30201994],"iteration":827,"passed_time":0.2843234443,"remaining_time":0.059062358},
{"learn":[3.299302297],"iteration":828,"passed_time":0.2845370134,"remaining_time":0.05869219457},
{"learn":[3.298132671],"iteration":829,"passed_time":0.2847753726,"remaining_time":0.05832748595},
{"learn":[3.296976183],"iteration":830,"passed_time":0.2849833587,"remaining_time":0.05795690448},
{"learn":[3.293144745],"iteration":831,"passed_time":0.2852000943,"remaining_time":0.05758848058},
{"learn":[3.290284404],"iteration":832,"passed_time":0.2854072472,"remaining_time":0.05721849973},
{"learn":[3.288285745],"iteration":833,"passed_time":0.2856438564,"remaining_time":0.05685477238},
{"learn":[3.286662667],"iteration":834,"passed_time":0.285920588,"remaining_time":0.05649927787},
{"learn":[3.285692682],"iteration":835,"passed_time":0.2861463646,"remaining_time":0.05613397584},
{"learn":[3.284565611],"iteration":836,"passed_time":0.2863697664,"remaining_time":0.05576854472},
{"learn":[3.283897383],"iteration":837,"passed_time":0.286591585,"remaining_time":0.0554031465},
{"learn":[3.280712855],"iteration":838,"passed_time":0.2868086539,"remaining_time":0.05503717911},
{"learn":[3.280468341],"iteration":839,"passed_time":0.2870295558,"remaining_time":0.05467229635},
{"learn":[3.277814895],"iteration":840,"passed_time":0.2872574157,"remaining_time":0.05430907145},
{"learn":[3.276316385],"iteration":841,"passed_time":0.2875120654,"remaining_time":0.05395119516},
{"learn":[3.27557063],"iteration":842,"passed_time":0.2877349255,"remaining_time":0.05358764331},
{"learn":[3.27499628],"iteration":843,"passed_time":0.2879669101,"remaining_time":0.05322611134},
{"learn":[3.273569958],"iteration":844,"passed_time":0.2882542659,"remaining_time":0.05287504287},
{"learn":[3.269665595],"iteration":845,"passed_time":0.2885124571,"remaining_time":0.05251881607},
{"learn":[3.267984685],"iteration":846,"passed_time":0.2887741063,"remaining_time":0.05216344542},
{"learn":[3.267702508],"iteration":847,"passed_time":0.2890192983,"remaining_time":0.05180534593},
{"learn":[3.266671924],"iteration":848,"passed_time":0.2892567409,"remaining_time":0.05144613412},
{"learn":[3.265359825],"iteration":849,"passed_time":0.2894930585,"remaining_time":0.05108701032},
{"learn":[3.2618983],"iteration":850,"passed_time":0.2897167519,"remaining_time":0.05072596479},
{"learn":[3.260456253],"iteration":851,"passed_time":0.2899336958,"remaining_time":0.05036406922},
{"learn":[3.258389147],"iteration":852,"passed_time":0.2901673469,"remaining_time":0.05000539273},
{"learn":[3.258108469],"iteration":853,"passed_time":0.2903869156,"remaining_time":0.0496446015},
{"learn":[3.256424936],"iteration":854,"passed_time":0.2907041862,"remaining_time":0.04930070993},
{"learn":[3.254817983],"iteration":855,"passed_time":0.2909477533,"remaining_time":0.04894448186},
{"learn":[3.253898449],"iteration":856,"passed_time":0.2911601558,"remaining_time":0.04858331655},
{"learn":[3.253023652],"iteration":857,"passed_time":0.2914419704,"remaining_time":0.04823398577},
{"learn":[3.252845542],"iteration":858,"passed_time":0.291683371,"remaining_time":0.04787817847},
{"learn":[3.252316026],"iteration":859,"passed_time":0.2919231467,"remaining_time":0.04752237271},
{"learn":[3.24975301],"iteration":860,"passed_time":0.2921702969,"remaining_time":0.04716802702},
{"learn":[3.249151075],"iteration":861,"passed_time":0.292409531,"remaining_time":0.04681266273},
{"learn":[3.246257135],"iteration":862,"passed_time":0.2926424321,"remaining_time":0.04645656222},
{"learn":[3.243826471],"iteration":863,"passed_time":0.2928653756,"remaining_time":0.04609917949},
{"learn":[3.243190653],"iteration":864,"passed_time":0.2931150256,"remaining_time":0.04574627568},
{"learn":[3.24008797],"iteration":865,"passed_time":0.293330553,"remaining_time":0.04538833037},
{"learn":[3.240036811],"iteration":866,"passed_time":0.2935594961,"remaining_time":0.0450327716},
{"learn":[3.238676314],"iteration":867,"passed_time":0.2937922306,"remaining_time":0.04467808114},
{"learn":[3.237848782],"iteration":868,"passed_time":0.2940975852,"remaining_time":0.04433461872},
{"learn":[3.236405498],"iteration":869,"passed_time":0.2943228202,"remaining_time":0.04397927199},
{"learn":[3.233378068],"iteration":870,"passed_time":0.2945778866,"remaining_time":0.04362864221},
{"learn":[3.233169169],"iteration":871,"passed_time":0.2948039965,"remaining_time":0.04327398114},
{"learn":[3.232434885],"iteration":872,"passed_time":0.2950373977,"remaining_time":0.04292067526},
{"learn":[3.229978115],"iteration":873,"passed_time":0.2952634243,"remaining_time":0.04256658062},
{"learn":[3.229648848],"iteration":874,"passed_time":0.2954751185,"remaining_time":0.04221073122},
{"learn":[3.227208761],"iteration":875,"passed_time":0.2957054782,"remaining_time":0.04185785307},
{"learn":[3.226258869],"iteration":876,"passed_time":0.2959200056,"remaining_time":0.04150303385},
{"learn":[3.225331995],"iteration":877,"passed_time":0.2962001536,"remaining_time":0.04115765232},
{"learn":[3.221968268],"iteration":878,"passed_time":0.2964208889,"remaining_time":0.04080424067},
{"learn":[3.221166317],"iteration":879,"passed_time":0.2966731637,"remaining_time":0.04045543142},
{"learn":[3.220047503],"iteration":880,"passed_time":0.296884983,"remaining_time":0.04010137681},
{"learn":[3.21982781],"iteration":881,"passed_time":0.2971035518,"remaining_time":0.03974854774},
{"learn":[3.216693405],"iteration":882,"passed_time":0.2973562849,"remaining_time":0.03940054964},
{"learn":[3.214798761],"iteration":883,"passed_time":0.2975756453,"remaining_time":0.03904838785},
{"learn":[3.214395085],"iteration":884,"passed_time":0.2977995471,"remaining_time":0.03869711629},
{"learn":[3.213470696],"iteration":885,"passed_time":0.2980167826,"remaining_time":0.03834527451},
{"learn":[3.211595017],"iteration":886,"passed_time":0.2982467673,"remaining_time":0.03799536043},
{"learn":[3.210965255],"iteration":887,"passed_time":0.2984974589,"remaining_time":0.03764832815},
{"learn":[3.209413583],"iteration":888,"passed_time":0.2987160694,"remaining_time":0.03729750698},
{"learn":[3.208331683],"iteration":889,"passed_time":0.2989405961,"remaining_time":0.03694771413},
{"learn":[3.207110711],"iteration":890,"passed_time":0.2991532486,"remaining_time":0.03659674983},
{"learn":[3.204519413],"iteration":891,"passed_time":0.2993941492,"remaining_time":0.03624951583},
{"learn":[3.201421296],"iteration":892,"passed_time":0.299617301,"remaining_time":0.03590039329},
{"learn":[3.200691259],"iteration":893,"passed_time":0.2998351199,"remaining_time":0.03555092025},
{"learn":[3.200485067],"iteration":894,"passed_time":0.3000549802,"remaining_time":0.03520198092},
{"learn":[3.197467568],"iteration":895,"passed_time":0.3002949226,"remaining_time":0.03485566066},
{"learn":[3.195838544],"iteration":896,"passed_time":0.300504117,"remaining_time":0.03450604688},
{"learn":[3.195671746],"iteration":897,"passed_time":0.300729602,"remaining_time":0.03415859622},
{"learn":[3.194213094],"iteration":898,"passed_time":0.3009641697,"remaining_time":0.03381243731},
{"learn":[3.192884691],"iteration":899,"passed_time":0.3011880298,"remaining_time":0.03346533664},
{"learn":[3.188364239],"iteration":900,"passed_time":0.3014058903,"remaining_time":0.03311785032},
{"learn":[3.185219478],"iteration":901,"passed_time":0.3016227509,"remaining_time":0.03277054278},
{"learn":[3.184120387],"iteration":902,"passed_time":0.3018394864,"remaining_time":0.03242351072},
{"learn":[3.183725321],"iteration":903,"passed_time":0.3020786372,"remaining_time":0.03207914731},
{"learn":[3.181264554],"iteration":904,"passed_time":0.302296456,"remaining_time":0.03173277715},
{"learn":[3.180741589],"iteration":905,"passed_time":0.3025101501,"remaining_time":0.03138626281},
{"learn":[3.179782639],"iteration":906,"passed_time":0.3027694245,"remaining_time":0.03104471497},
{"learn":[3.176377564],"iteration":907,"passed_time":0.303041823,"remaining_time":0.03070467811},
{"learn":[3.174078182],"iteration":908,"passed_time":0.3032784323,"remaining_time":0.03036120719},
{"learn":[3.171242379],"iteration":909,"passed_time":0.3035104168,"remaining_time":0.03001751375},
{"learn":[3.170421012],"iteration":910,"passed_time":0.3037262775,"remaining_time":0.02967249033},
{"learn":[3.170087224],"iteration":911,"passed_time":0.3039758442,"remaining_time":0.02933100251},
{"learn":[3.167303059],"iteration":912,"passed_time":0.3042202029,"remaining_time":0.02898921977},
{"learn":[3.16705966],"iteration":913,"passed_time":0.304434272,"remaining_time":0.02864480021},
{"learn":[3.165667683],"iteration":914,"passed_time":0.3046528824,"remaining_time":0.02830108744},
{"learn":[3.164689733],"iteration":915,"passed_time":0.3048783258,"remaining_time":0.02795827441},
{"learn":[3.163311455],"iteration":916,"passed_time":0.3051154766,"remaining_time":0.02761677706},
{"learn":[3.159425016],"iteration":917,"passed_time":0.3053493361,"remaining_time":0.02727521303},
{"learn":[3.159327058],"iteration":918,"passed_time":0.3055826955,"remaining_time":0.02693383932},
{"learn":[3.15819426],"iteration":919,"passed_time":0.3058338871,"remaining_time":0.02659425106},
{"learn":[3.157086603],"iteration":920,"passed_time":0.3060485812,"remaining_time":0.02625172412},
{"learn":[3.153354154],"iteration":921,"passed_time":0.3062593171,"remaining_time":0.02590913963},
{"learn":[3.153261317],"iteration":922,"passed_time":0.3065185082,"remaining_time":0.02557088313},
{"learn":[3.153168454],"iteration":923,"passed_time":0.3067454931,"remaining_time":0.02523014878},
{"learn":[3.152080399],"iteration":924,"passed_time":0.3069668117,"remaining_time":0.02488920095},
{"learn":[3.151635144],"iteration":925,"passed_time":0.3071883803,"remaining_time":0.02454853147},
{"learn":[3.147762655],"iteration":926,"passed_time":0.3074246562,"remaining_time":0.02420927714},
{"learn":[3.147172317],"iteration":927,"passed_time":0.3076711398,"remaining_time":0.02387103671},
{"learn":[3.146254125],"iteration":928,"passed_time":0.3079087907,"remaining_time":0.02353231877},
{"learn":[3.144869828],"iteration":929,"passed_time":0.3081414835,"remaining_time":0.02319344499},
{"learn":[3.143466218],"iteration":930,"passed_time":0.3083486364,"remaining_time":0.02285290645},
{"learn":[3.141919643],"iteration":931,"passed_time":0.3085924118,"remaining_time":0.02251532618},
{"learn":[3.141054135],"iteration":932,"passed_time":0.3088413119,"remaining_time":0.022178315},
{"learn":[3.139390417],"iteration":933,"passed_time":0.30906938,"remaining_time":0.02184002043},
{"learn":[3.139025283],"iteration":934,"passed_time":0.3093416536,"remaining_time":0.02150503474},
{"learn":[3.137824183],"iteration":935,"passed_time":0.3096001364,"remaining_time":0.02116924009},
{"learn":[3.135620453],"iteration":936,"passed_time":0.3098372039,"remaining_time":0.02083217059},
{"learn":[3.13443178],"iteration":937,"passed_time":0.3100694385,"remaining_time":0.02049499487},
{"learn":[3.132765713],"iteration":938,"passed_time":0.3102932986,"remaining_time":0.02015749863},
{"learn":[3.131434124],"iteration":939,"passed_time":0.3105296578,"remaining_time":0.01982104199},
{"learn":[3.128384262],"iteration":940,"passed_time":0.3107827243,"remaining_time":0.01948584563},
{"learn":[3.128120455],"iteration":941,"passed_time":0.3109812528,"remaining_time":0.01914746567},
{"learn":[3.126314615],"iteration":942,"passed_time":0.3112325694,"remaining_time":0.01881257312},
{"learn":[3.125409666],"iteration":943,"passed_time":0.3114595542,"remaining_time":0.01847641423},
{"learn":[3.123072589],"iteration":944,"passed_time":0.3116864975,"remaining_time":0.01814048398},
{"learn":[3.122921099],"iteration":945,"passed_time":0.3119208152,"remaining_time":0.0178052051},
{"learn":[3.122182662],"iteration":946,"passed_time":0.3121578411,"remaining_time":0.017470291},
{"learn":[3.120040951],"iteration":947,"passed_time":0.3123777848,"remaining_time":0.01713464642},
{"learn":[3.118767799],"iteration":948,"passed_time":0.3126414755,"remaining_time":0.01680159668},
{"learn":[3.118203218],"iteration":949,"passed_time":0.3128789181,"remaining_time":0.01646731148},
{"learn":[3.116343362],"iteration":950,"passed_time":0.3131513166,"remaining_time":0.01613503103},
{"learn":[3.11480829],"iteration":951,"passed_time":0.3133898007,"remaining_time":0.01580116642},
{"learn":[3.112607903],"iteration":952,"passed_time":0.3135986202,"remaining_time":0.01546603898},
{"learn":[3.111661241],"iteration":953,"passed_time":0.3138375626,"remaining_time":0.0151326288},
{"learn":[3.110249676],"iteration":954,"passed_time":0.3140737552,"remaining_time":0.01479928689},
{"learn":[3.107333579],"iteration":955,"passed_time":0.3143092812,"remaining_time":0.01446611754},
{"learn":[3.107149851],"iteration":956,"passed_time":0.3145361827,"remaining_time":0.01413276474},
{"learn":[3.106867336],"iteration":957,"passed_time":0.3147618344,"remaining_time":0.01379957938},
{"learn":[3.10364681],"iteration":958,"passed_time":0.3149969854,"remaining_time":0.0134670244},
{"learn":[3.102703811],"iteration":959,"passed_time":0.3152193456,"remaining_time":0.0131341394},
{"learn":[3.101469264],"iteration":960,"passed_time":0.3154407058,"remaining_time":0.01280144384},
{"learn":[3.09863569],"iteration":961,"passed_time":0.3156598162,"remaining_time":0.01246889087},
{"learn":[3.09645939],"iteration":962,"passed_time":0.3158720938,"remaining_time":0.01213631098},
{"learn":[3.096240186],"iteration":963,"passed_time":0.3160987037,"remaining_time":0.01180451591},
{"learn":[3.094838828],"iteration":964,"passed_time":0.3163238137,"remaining_time":0.01147288443},
{"learn":[3.094176802],"iteration":965,"passed_time":0.3165432574,"remaining_time":0.01114127407},
{"learn":[3.093182279],"iteration":966,"passed_time":0.316785283,"remaining_time":0.01081066633},
{"learn":[3.090150687],"iteration":967,"passed_time":0.3169949774,"remaining_time":0.0104791728},
{"learn":[3.088612829],"iteration":968,"passed_time":0.3172391278,"remaining_time":0.01014903298},
{"learn":[3.087153684],"iteration":969,"passed_time":0.3174588631,"remaining_time":0.009818315355},
{"learn":[3.085866843],"iteration":970,"passed_time":0.317685473,"remaining_time":0.009488031636},
{"learn":[3.082669094],"iteration":971,"passed_time":0.3179277486,"remaining_time":0.00915841251},
{"learn":[3.081047548],"iteration":972,"passed_time":0.3181597748,"remaining_time":0.008828688509},
{"learn":[3.079684322],"iteration":973,"passed_time":0.3184038835,"remaining_time":0.008499487651},
{"learn":[3.07613431],"iteration":974,"passed_time":0.3186395345,"remaining_time":0.008170244475},
{"learn":[3.074005935],"iteration":975,"passed_time":0.3188848099,"remaining_time":0.007841429751},
{"learn":[3.072988853],"iteration":976,"passed_time":0.3191063784,"remaining_time":0.007512227947},
{"learn":[3.072344268],"iteration":977,"passed_time":0.3193254472,"remaining_time":0.007183190018},
{"learn":[3.070654438],"iteration":978,"passed_time":0.3195447659,"remaining_time":0.006854382108},
{"learn":[3.069724506],"iteration":979,"passed_time":0.3197994573,"remaining_time":0.006526519537},
{"learn":[3.067763166],"iteration":980,"passed_time":0.3200610649,"remaining_time":0.006198940094},
{"learn":[3.066737893],"iteration":981,"passed_time":0.3202633014,"remaining_time":0.005870406747},
{"learn":[3.065248174],"iteration":982,"passed_time":0.3204814535,"remaining_time":0.005542405606},
{"learn":[3.063186837],"iteration":983,"passed_time":0.3207016056,"remaining_time":0.005214660253},
{"learn":[3.062880371],"iteration":984,"passed_time":0.3209166329,"remaining_time":0.004887055323},
{"learn":[3.061288645],"iteration":985,"passed_time":0.3211338268,"remaining_time":0.004559709508},
{"learn":[3.059970575],"iteration":986,"passed_time":0.3213508123,"remaining_time":0.004232584154},
{"learn":[3.059576341],"iteration":987,"passed_time":0.3215661313,"remaining_time":0.003905661514},
{"learn":[3.058175919],"iteration":988,"passed_time":0.3218389465,"remaining_time":0.003579604056},
{"learn":[3.056830702],"iteration":989,"passed_time":0.32206189,"remaining_time":0.003253150404},
{"learn":[3.056336579],"iteration":990,"passed_time":0.3222881249,"remaining_time":0.002926935544},
{"learn":[3.055810414],"iteration":991,"passed_time":0.3225120267,"remaining_time":0.002600903441},
{"learn":[3.055476518],"iteration":992,"passed_time":0.3227214711,"remaining_time":0.002274975123},
{"learn":[3.053331734],"iteration":993,"passed_time":0.3229260824,"remaining_time":0.001949252007},
{"learn":[3.050890374],"iteration":994,"passed_time":0.3231461928,"remaining_time":0.001623850215},
{"learn":[3.04972623],"iteration":995,"passed_time":0.3233591786,"remaining_time":0.001298631239},
{"learn":[3.047217327],"iteration":996,"passed_time":0.3235868718,"remaining_time":0.0009736816603},
{"learn":[3.047155483],"iteration":997,"passed_time":0.323814565,"remaining_time":0.0006489269839},
{"learn":[3.04430671],"iteration":998,"passed_time":0.3240168848,"remaining_time":0.000324341226},
{"learn":[3.042664195],"iteration":999,"passed_time":0.324223746,"remaining_time":0}
]}